Workbook
Name AUD: FX!$C$5
Name CHF: FX!$C$3
Name CNY: FX!$C$11
Name DKK: FX!$C$2
Name DKKUSD: #REF!
Name EUR: FX!$C$4
Name GBP: FX!$C$6
Name HKD: FX!$C$8
Name INR: FX!$C$10
Name JPY: FX!$C$7
Name KRW: FX!$C$9

Sheet Main
D2: =RANDBETWEEN(1,D257) -> 169 | H2: =SUM(H5:H419)-H10-H8-H13-H19-H23-H26-H52-H57 -> 4704489.9 | M2: =MIN(M5:M87) -> 45535 | O2: =AVERAGE(O5:O25) -> 0.069210709 | S2: EV/EPS | Y2: EPS
B3: R | C3: C | E3: Name | F3: Ticker | G3: Price | H3: MC | I3: NC | J3: EV | K3: Update | L3: SO | M3: Last | N3: NPV | O3: Upside | P3: ROIC | Q3: Terminal | R3: Discount | S3: 2022 | T3: 2023 | U3: 2024 | V3: 2025 | W3: 2026 | X3: 2027 | Y3: 2022 | Z3: 2023 | AA3: 2024 | AB3: 2025 | AC3: 2026 | AD3: 2027 | AE3: Founded | AF3: Location
S4: =TRIMMEAN(S5:S301,10%) -> 39.229343 | T4: =TRIMMEAN(T5:T301,10%) -> 85.398914 | U4: =TRIMMEAN(U5:U301,10%) -> 50.025711 | V4: =TRIMMEAN(V5:V301,10%) -> 17.311967 | W4: =TRIMMEAN(W5:W301,10%) -> 15.537076 | X4: =TRIMMEAN(X5:X301,10%) -> 14.509885 | Y4: - | Z4: - | AA4: - | AB4: - | AC4: - | AD4: - | AE4: =AVERAGE(AE5:AE222) -> 1969.4722
A5: x | D5: 1 | E5: Eli Lilly | F5: LLY | G5: 707 | H5: =+G5*L5 -> 636724.2 | I5: =+[1]Main!$J$5-[1]Main!$J$6 -> -32073 | J5: =H5-I5 -> 668797.2 | K5: Q125 | L5: =+[1]Main!$J$3 -> 900.6 | M5: 45873 | N5: =[1]Model!$FY$101 -> 929.05463 | O5: =+N5/G5-1 -> 0.31408011 | P5: =[1]Model!$FY$97 -> 0.02 | Q5: =[1]Model!$FY$98 -> 0 | R5: =[1]Model!$FY$99 -> 0.07 | S5: =($J5/$L5)/Y5 -> 107.62506 | T5: =($J5/$L5)/Z5 -> 128.03671 | U5: =($J5/$L5)/AA5 -> 63.416988 | V5: =($J5/$L5)/AB5 -> 34.064813 | W5: =($J5/$L5)/AC5 -> 25.037523 | X5: - | Y5: 6.9 | Z5: 5.8 | AA5: 11.71 | AB5: 21.8 | AC5: 29.66 | AD5: - | AE5: 1876
A6: x | D6: 2 | E6: J&J | F6: JNJ | G6: 176.12 | H6: =+G6*L6 -> 423744.72 | I6: =+[2]Main!$L$5-[2]Main!$L$6 -> -13471 | J6: =H6-I6 -> 437215.72 | K6: Q125 | L6: =+[2]Main!$L$3 -> 2406 | M6: 45875 | N6: =[2]Model!$FN$86 -> 0 | O6: =N6/G6-1 -> -1 | P6: =[2]Model!$FN$78 -> 2552.9 | Q6: =[2]Model!$FN$79 -> 0 | R6: =[2]Model!$FN$80 -> 0 | S6: =($J6/$L6)/Y6 -> 27.001325 | T6: =($J6/$L6)/Z6 -> 32.860564 | U6: =($J6/$L6)/AA6 -> 31.38496 | V6: =($J6/$L6)/AB6 -> 17.127137 | W6: =($J6/$L6)/AC6 -> 16.371074 | X6: =($J6/$L6)/AD6 -> 15.889201 | Y6: 6.73 | Z6: 5.53 | AA6: 5.79 | AB6: 10.61 | AC6: 11.1 | AD6: =+[2]Model!$FB$77 -> 11.43663 | AE6: 1886
A7: x | D7: 3 | E7: AbbVie | F7: ABBV | G7: 203.44 | H7: =+G7*L7 -> 360495.68 | I7: =+[3]Main!$K$5-[3]Main!$K$6 -> -64426 | J7: =H7-I7 -> 424921.68 | K7: Q125 | L7: =+[3]Main!$K$3 -> 1772 | M7: 45789 | N7: =[3]Model!$DT$78 -> 229.98813 | O7: =+N7/G7-1 -> 0.13049613 | P7: =[3]Model!$DT$76 -> 0 | Q7: =[3]Model!$DT$75 -> -0.01 | R7: =[3]Model!$DT$74 -> 0.06 | S7: =($J7/$L7)/Y7 -> 36.168595 | T7: =($J7/$L7)/Z7 -> 88.160951 | U7: =($J7/$L7)/AA7 -> 100.3338 | V7: =($J7/$L7)/AB7 -> 19.607342 | W7: =($J7/$L7)/AC7 -> 17.140657 | X7: - | Y7: 6.63 | Z7: 2.72 | AA7: 2.39 | AB7: 12.23 | AC7: 13.99 | AD7: - | AE7: 1888
A8: x | D8: =+D7+1 -> 4 | E8: AstraZeneca | F8: AZN | G8: 74.66 | H8: =+G8*L8*2 -> 232939.2 | I8: =+[4]Main!$K$5-[4]Main!$K$6 -> -26067 | J8: =H8-I8 -> 259006.2 | K8: Q125 | L8: =+[4]Main!$K$3 -> 1560 | M8: 45820 | S8: =($J8/$L8)/Y8 -> 156.63171 | T8: =($J8/$L8)/Z8 -> 86.473758 | U8: =($J8/$L8)/AA8 -> 73.1408 | V8: =($J8/$L8)/AB8 -> 36.813662 | W8: =($J8/$L8)/AC8 -> 32.618785 | X8: - | Y8: 1.06 | Z8: 1.92 | AA8: 2.27 | AB8: 4.51 | AC8: 5.09 | AD8: -
A9: x | D9: =+D8 -> 4 | E9: AstraZeneca | F9: AZN LN | G9: 11136 | H9: =+G9*L9/100*GBP -> 225838.08 | I9: =+[4]Main!$K$5-[4]Main!$K$6 -> -26067 | J9: =H9-I9 -> 251905.08 | K9: =+K8 -> Q125 | L9: =+[4]Main!$K$3 -> 1560 | M9: =+M8 -> 45820 | N9: - | O9: - | P9: - | Q9: - | R9: - | S9: - | T9: - | U9: - | V9: - | W9: - | X9: - | Y9: - | Z9: - | AA9: - | AB9: - | AC9: - | AD9: -
A10: x | D10: =+D9+1 -> 5 | E10: Novo Nordisk | F10: NVO | G10: 47.39 | H10: =+L10*G10 -> 210695.94 | I10: =([5]Main!$J$5-[5]Main!$J$6)/DKK -> -10378.206 | J10: =H10-I10 -> 221074.15 | K10: Q324 | L10: =+[5]Main!$J$3 -> 4446 | M10: 45671 | N10: - | O10: - | P10: - | Q10: - | R10: - | S10: =($J10/$L10)/Y10 -> 28.742358 | T10: =($J10/$L10)/Z10 -> 18.348443 | U10: =($J10/$L10)/AA10 -> 15.113763 | V10: =($J10/$L10)/AB10 -> 12.493538 | W10: =($J10/$L10)/AC10 -> 10.534805 | X10: - | Y10: 1.73 | Z10: 2.71 | AA10: 3.29 | AB10: 3.98 | AC10: 4.72 | AD10: - | AE10: 1923
A11: x | D11: =+D10 -> 5 | E11: Novo Nordisk | F11: NOVOB | G11: 313 | H11: =+G11*L11/DKK -> 197193.99 | I11: =([5]Main!$J$5-[5]Main!$J$6)/DKK -> -10378.206 | J11: =H11-I11 -> 207572.2 | K11: =+K10 -> Q324 | L11: =+[5]Main!$J$3 -> 4446 | M11: =+M10 -> 45671 | N11: =+[5]Model!$DM$53 -> 443.65753 | O11: =N11/G11-1 -> 0.41743621 | P11: =[5]Model!$DM$49*-1 -> 0.01 | Q11: =+[5]Model!$DM$50 -> -0.01 | R11: =+[5]Model!$DM$51 -> 0.08 | S11: - | T11: - | U11: - | V11: - | W11: - | X11: - | Y11: - | Z11: - | AA11: - | AB11: - | AC11: - | AD11: - | AE11: 1923
A12: x | D12: =+D11+1 -> 6 | E12: Roche | F12: ROG VX | G12: 268 | H12: =+L12*G12 -> 214508 | I12: =+[6]Main!$J$5-[6]Main!$J$6 -> -17337 | J12: =H12-I12 -> 231845 | K12: Q423 | L12: =+[6]Main!$J$3 -> 800.403 | M12: 45754 | S12: - | T12: - | U12: =($J12/$L12)/AA12 -> 15.665784 | V12: =($J12/$L12)/AB12 -> 14.475779 | W12: =($J12/$L12)/AC12 -> 13.599077 | X12: =($J12/$L12)/AD12 -> 13.130568 | Y12: - | Z12: - | AA12: 18.49 | AB12: 20.01 | AC12: 21.3 | AD12: 22.06 | AE12: 1896
A13: x | D13: =+D12+1 -> 7 | E13: Novartis | F13: NVS | G13: 117.92 | H13: =+G13*L13 -> 231035.22 | I13: =+[7]Main!$K$6-[7]Main!$K$7 -> -22271 | J13: =H13-I13 -> 253306.22 | K13: Q125 | L13: =+[7]Main!$K$4 -> 1959.2539 | M13: 45793 | S13: =($J13/$L13)/Y13 -> 40.528866 | T13: =($J13/$L13)/Z13 -> 18.082109 | U13: =($J13/$L13)/AA13 -> 21.839034 | V13: =($J13/$L13)/AB13 -> 14.929224 | W13: =($J13/$L13)/AC13 -> 14.349288 | X13: - | Y13: 3.19 | Z13: 7.15 | AA13: 5.92 | AB13: 8.66 | AC13: 9.01 | AD13: -
A14: x | D14: =+D13 -> 7 | E14: Novartis | F14: NOVN VX | G14: 94.58 | H14: =+G14*L14/CHF -> 203633.22 | I14: =+[7]Main!$K$6-[7]Main!$K$7 -> -22271 | J14: =H14-I14 -> 225904.22 | K14: Q125 | L14: =+[7]Main!$K$4 -> 1959.2539 | M14: =+M13 -> 45793 | N14: - | O14: - | P14: - | Q14: - | R14: - | S14: - | T14: - | U14: - | V14: - | W14: - | X14: - | Y14: - | Z14: - | AA14: - | AB14: - | AC14: - | AD14: -
A15: x | D15: =+D14+1 -> 8 | E15: Merck | F15: MRK | G15: 85 | H15: =+G15*L15 -> 215135 | I15: =+[8]Main!$J$5-[8]Main!$J$6 -> -26006 | J15: =H15-I15 -> 241141 | K15: Q424 | L15: =+[8]Main!$J$3 -> 2531 | M15: 45771 | N15: =[8]Model!$EM$113 -> 91.467148 | O15: =N15/G15-1 -> 0.076084093 | P15: =[8]Model!$EM$109 -> 0.01 | Q15: =[8]Model!$EM$110 -> -0.01 | R15: =[8]Model!$EM$111 -> 0.07 | S15: =($J15/$L15)/Y15 -> 16.685637 | T15: =($J15/$L15)/Z15 -> 680.53564 | U15: =($J15/$L15)/AA15 -> 14.135755 | V15: =($J15/$L15)/AB15 -> 10.705055 | W15: =($J15/$L15)/AC15 -> 9.8019537 | X15: - | Y15: 5.71 | Z15: 0.14 | AA15: 6.74 | AB15: 8.9 | AC15: 9.72 | AD15: - | AE15: 1919
A16: x | D16: =+D15+1 -> 9 | E16: Amgen | F16: AMGN | G16: 300 | H16: =+G16*L16 -> 162300 | I16: =[9]Main!$J$5-[9]Main!$J$6 -> -48571 | J16: =H16-I16 -> 210871 | K16: Q125 | L16: =[9]Main!$J$3 -> 541 | M16: 45804 | N16: =+[9]Model!$EM$60 -> 296.41443 | O16: =N16/G16-1 -> -0.011951887 | P16: =+[9]Model!$EM$56 -> 0.01 | Q16: =+[9]Model!$EM$57 -> -0.02 | R16: =+[9]Model!$EM$58 -> 0.08 | S16: =($J16/$L16)/Y16 -> 32.186626 | T16: =($J16/$L16)/Z16 -> 31.207369 | U16: =($J16/$L16)/AA16 -> 51.558206 | V16: =($J16/$L16)/AB16 -> 18.694486 | W16: =($J16/$L16)/AC16 -> 18.112455 | X16: - | Y16: 12.11 | Z16: 12.49 | AA16: 7.56 | AB16: 20.85 | AC16: 21.52 | AD16: - | AE16: 1980
A17: x | D17: =+D16+1 -> 10 | E17: Pfizer | F17: PFE | G17: 24.48 | H17: =+L17*G17 -> 139780.8 | I17: =+[10]Main!$K$5-[10]Main!$K$6 -> -42779 | J17: =H17-I17 -> 182559.8 | K17: Q125 | L17: =+[10]Main!$K$3 -> 5710 | M17: 45805 | S17: =($J17/$L17)/Y17 -> 5.8449623 | T17: =($J17/$L17)/Z17 -> 84.136695 | U17: =($J17/$L17)/AA17 -> 22.675138 | V17: =($J17/$L17)/AB17 -> 10.657315 | W17: =($J17/$L17)/AC17 -> 10.380501 | X17: - | Y17: 5.47 | Z17: 0.38 | AA17: 1.41 | AB17: 3 | AC17: 3.08 | AD17: -
A18: x | D18: =+D17+1 -> 11 | E18: Gilead | F18: GILD | G18: 113.75 | H18: =+G18*L18 -> 143211.25 | I18: =+[11]Main!$J$5-[11]Main!$J$6 -> -16720 | J18: =H18-I18 -> 159931.25 | K18: Q424 | L18: =+[11]Main!$J$3 -> 1259 | M18: 45768 | S18: =($J18/$L18)/Y18 -> 34.898456 | T18: =($J18/$L18)/Z18 -> 28.228974 | U18: =($J18/$L18)/AA18 -> 334.29048 | V18: =($J18/$L18)/AB18 -> 15.898671 | W18: =($J18/$L18)/AC18 -> 14.909669 | X18: - | Y18: 3.64 | Z18: 4.5 | AA18: 0.38 | AB18: 7.99 | AC18: 8.52 | AD18: -
A19: x | D19: =+D18+1 -> 12 | E19: Sanofi | F19: SAN | G19: 82 | H19: =G19*[12]Main!$K$3*EUR -> 113866.02 | I19: =([13]Main!$K$5-[13]Main!$K$6)*EUR -> -12746.13 | J19: =H19-I19 -> 126612.15 | K19: Q224 | L19: =+[12]Main!$K$3 -> 1251 | M19: 45776 | S19: - | T19: - | U19: - | V19: =($J19/$L19)/AB19 -> 22.097981 | W19: =($J19/$L19)/AC19 -> 20.121024 | X19: - | Y19: - | Z19: - | AA19: - | AB19: 4.58 | AC19: 5.03 | AD19: -
A20: x | D20: =+D19 -> 12 | E20: Sanofi | F20: SNY | G20: 47.76 | H20: =+G20*L20*2 -> 119495.52 | I20: =([13]Main!$K$5-[13]Main!$K$6)*EUR -> -12746.13 | J20: =H20-I20 -> 132241.65 | K20: =+K19 -> Q224 | L20: =+L19 -> 1251 | M20: =+M19 -> 45776 | N20: - | O20: - | P20: - | Q20: - | R20: - | S20: - | T20: - | U20: - | V20: - | W20: - | X20: - | Y20: - | Z20: - | AA20: - | AB20: - | AC20: - | AD20: -
A21: x | D21: =+D20+1 -> 13 | E21: Bristol-Myers | F21: BMY | G21: 45.38 | H21: =+G21*L21 -> 92076.02 | I21: =+[14]Main!$K$5-[14]Main!$K$6 -> -38470 | J21: =H21-I21 -> 130546.02 | K21: Q424 | L21: =+[14]Main!$K$3 -> 2029 | M21: 45771 | S21: =($J21/$L21)/Y21 -> 21.810196 | T21: =($J21/$L21)/Z21 -> 16.668414 | U21: =($J21/$L21)/AA21 -> -14.589587 | V21: =($J21/$L21)/AB21 -> 9.3790202 | W21: =($J21/$L21)/AC21 -> 10.599684 | X21: - | Y21: 2.95 | Z21: 3.86 | AA21: -4.41 | AB21: 6.86 | AC21: 6.07 | AD21: - | AE21: 1887
A22: x | D22: =+D21+1 -> 14 | E22: Vertex | F22: VRTX | G22: 401 | H22: =+G22*[15]Main!$M$3 -> 102975.67 | I22: =+[15]Main!$M$5-[15]Main!$M$6 -> 11358 | J22: =H22-I22 -> 91617.672 | K22: Q125 | L22: =+[15]Main!$M$3 -> 256.79719 | M22: 45789 | N22: =+[15]Model!$BK$34 -> 624.89046 | O22: =N22/G22-1 -> 0.55833032 | P22: =+[15]Model!$BK$32 -> 0.03 | Q22: =+[15]Model!$BK$30 -> -0.05 | R22: =[15]Model!$BK$30 -> -0.05 | S22: =($J22/$L22)/Y22 -> 27.829216 | T22: =($J22/$L22)/Z22 -> 25.685424 | U22: =($J22/$L22)/AA22 -> 30.132647 | V22: =($J22/$L22)/AB22 -> 19.831603 | W22: =($J22/$L22)/AC22 -> 17.144188 | X22: - | Y22: 12.82 | Z22: 13.89 | AA22: =-2.08+13.92 -> 11.84 | AB22: 17.99 | AC22: 20.81 | AD22: -
A23: x | D23: =+D22+1 -> 15 | E23: GSK | F23: GSK US | G23: 37.44 | H23: =+G23*L23/2 -> 77444.64 | I23: =([16]Main!$J$6-[16]Main!$J$7)*GBP -> -18131.1 | J23: =H23-I23 -> 95575.74 | K23: Q125 | L23: =+[16]Main!$J$4 -> 4137 | M23: 45805 | S23: =($J23/$L23)/Y23 -> 6.6964257 | T23: =($J23/$L23)/Z23 -> 5.9851473 | U23: =($J23/$L23)/AA23 -> 5.6763314 | V23: =($J23/$L23)/AB23 -> 5.1683822 | W23: =($J23/$L23)/AC23 -> 4.6766536 | X23: - | Y23: 3.45 | Z23: 3.86 | AA23: 4.07 | AB23: 4.47 | AC23: 4.94 | AD23: 5.35
A24: x | D24: =+D23 -> 15 | E24: GSK | F24: GSK LN | G24: 1398 | H24: =+G24*L24/100*GBP -> 75185.838 | I24: =([16]Main!$J$6-[16]Main!$J$7)*GBP -> -18131.1 | J24: =H24-I24 -> 93316.938 | K24: =+K23 -> Q125 | L24: =+L23 -> 4137 | M24: =+M23 -> 45805 | N24: - | O24: - | P24: - | Q24: - | R24: - | S24: =($J24/$L24)/Y24 -> 16.111906 | T24: =($J24/$L24)/Z24 -> 14.552689 | U24: =($J24/$L24)/AA24 -> 14.186584 | V24: =($J24/$L24)/AB24 -> 13.670708 | W24: =($J24/$L24)/AC24 -> 12.393774 | X24: - | Y24: 1.4 | Z24: 1.55 | AA24: 1.59 | AB24: 1.65 | AC24: 1.82 | AD24: 1.97
A25: x | D25: =+D24+1 -> 16 | E25: CSL | F25: CSL AU | G25: 264.91 | H25: =+G25*L25*AUD -> 86117.879 | I25: =[17]Main!$J$5-[17]Main!$J$6 -> -10363 | J25: =H25-I25 -> 96480.879 | K25: Q224 | L25: =+[17]Main!$J$3 -> 485.19931 | M25: 45822 | S25: =($J25/$L25)/Y25 -> 29.678796 | T25: =($J25/$L25)/Z25 -> 22.020812 | U25: =($J25/$L25)/AA25 -> 21.450694 | V25: =($J25/$L25)/AB25 -> 18.688716 | W25: =($J25/$L25)/AC25 -> 16.339189 | X25: - | Y25: 6.7 | Z25: 9.03 | AA25: 9.27 | AB25: 10.64 | AC25: 12.17 | AD25: 13.65
A26: x | D26: =+D25+1 -> 17 | E26: Takeda | F26: TAK | G26: 14.23 | H26: =+G26*2*L26 -> 44653.74 | I26: =([18]Main!$K$6-[18]Main!$K$7)/JPY -> -27370.052 | J26: =+H26-I26 -> 72023.792 | K26: Q224 | L26: =+[18]Main!$K$4 -> 1569 | M26: 45812
A27: x | D27: =+D26 -> 17 | E27: Takeda | F27: 4502 JP | G27: 4219 | H27: =+G27*L27/JPY -> 45573.914 | I27: =([18]Main!$K$6-[18]Main!$K$7)/JPY -> -27370.052 | J27: =+H27-I27 -> 72943.966 | K27: Q224 | L27: =+[18]Main!$K$4 -> 1569 | M27: =+M26 -> 45812
A28: x | D28: =+D27+1 -> 18 | E28: Chugai | F28: 4519 JP | G28: 7303 | H28: =+G28*L28/JPY -> 82728.416 | I28: =([19]Main!$J$5-[19]Main!$J$6)/JPY -> 5615.5456 | J28: =+H28-I28 -> 77112.87 | K28: Q224 | L28: =+[19]Main!$J$3 -> 1645.3926 | M28: 45537 | AE28: 1925
A29: x | D29: =+D28+1 -> 19 | E29: Merck KgAa | F29: MRK DE | G29: 108.45 | H29: =+G29*L29 -> 47175.75 | I29: =([20]Main!$J$5-[20]Main!$J$6)*EUR -> -7904.421 | J29: =H29-I29 -> 55080.171 | K29: Q125 | L29: 435 | M29: 45822
A30: x | D30: =+D29+1 -> 20 | E30: Bayer | F30: BAYN | G30: 27.4 | H30: =+G30*L30*EUR -> 29879.322 | I30: =([21]Main!$J$5-[21]Main!$J$6) -> -34255 | J30: =+H30-I30 -> 64134.322 | K30: Q125 | L30: =+[21]Main!$J$3 -> 982.42 | M30: 45822
A31: x | D31: =+D30+1 -> 21 | E31: Regeneron | F31: REGN | G31: 571.62 | H31: =+G31*L31 -> 63564.144 | I31: =+[22]Main!$J$5-[22]Main!$J$6 -> 15641 | J31: =H31-I31 -> 47923.144 | K31: Q125 | L31: =+[22]Main!$J$3 -> 111.2 | M31: 45776 | AE31: 1988
A32: x | D32: =+D31+1 -> 22 | E32: Sun Pharmaceuticals | F32: SUNP | G32: 1641.6 | H32: {=+G32*L32/INR} -> 47706.825 | I32: =([23]Main!$J$5-[23]Main!$J$6)/INR -> 361.34101 | J32: =H32-I32 -> 47345.484 | K32: Q224 | L32: =+[23]Main!$J$3 -> 2399 | M32: 45537 | AE32: 1983
A33: x | D33: =+D32+1 -> 23 | E33: Samsung Biologics | F33: 207940 KS | G33: 1048000 | H33: =+G33*L33/KRW -> 52051.886 | I33: =([24]Main!$M$5-[24]Main!$M$6)/KRW*1000 -> 439.56164 | J33: =+H33-I33 -> 51612.324 | K33: Q124 | L33: =+[24]Main!$M$3 -> 71.174 | M33: 45536
A34: x | D34: =+D33+1 -> 24 | E34: Daiichi Sankyo | F34: 4568 JP | G34: 3620 | H34: =+G34*L34/JPY -> 47710.798 | I34: =([25]Main!$M$5-[25]Main!$M$6)*1000/JPY -> 6914.7608 | J34: =+H34-I34 -> 40796.038 | K34: Q224 | L34: =+[25]Main!$M$3 -> 1914.3628 | M34: 45535
A35: x | D35: =+D34+1 -> 25 | E35: UCB | F35: UCB | G35: 184.65 | H35: =+G35*L35*EUR -> 38942.685 | I35: =([26]Main!$J$5-[26]Main!$J$6)*EUR -> -2901.54 | J35: =H35-I35 -> 41844.225 | K35: Q224 | L35: =+[26]Main!$J$3 -> 190 | M35: 45537
A36: x | D36: =+D35+1 -> 26 | E36: Teva | F36: TEVA | G36: 15.9 | H36: =+G36*L36 -> 18014.7 | I36: =+[27]Main!$M$5-[27]Main!$M$6 -> -16382 | J36: =+H36-I36 -> 34396.7 | K36: Q125 | L36: =+[27]Main!$M$3 -> 1133 | M36: 45793
A37: x | D37: =+D36+1 -> 27 | E37: Alnylam | F37: ALNY | G37: 420.99 | H37: =+G37*L37 -> 54859.628 | I37: =+[28]Main!$L$5-[28]Main!$L$6 -> 1606.656 | J37: =H37-I37 -> 53252.972 | K37: Q125 | L37: =+[28]Main!$L$3 -> 130.311 | M37: 45821 | AE37: 2002 | AF37: Cambridge, MA
A38: x | D38: =+D37+1 -> 28 | E38: Argenx | F38: ARGX | G38: 693 | H38: =+G38*L38 -> 41649.3 | I38: =+[29]Main!$K$5-[29]Main!$K$6 -> 3374 | J38: =H38-I38 -> 38275.3 | K38: Q324 | L38: =+[29]Main!$K$3 -> 60.1 | M38: 45757 | AE38: 2008
A39: x | D39: =+D38+1 -> 29 | E39: Baxter | F39: BAX | G39: 22.66 | H39: =+G39*L39 -> 11556.6 | I39: =+[30]Main!$K$5-[30]Main!$K$6 -> -10809 | J39: =+H39-I39 -> 22365.6 | K39: Q224 | L39: =+[30]Main!$K$3 -> 510 | M39: 45536 | AE39: 1931
A40: x | D40: =+D39+1 -> 30 | E40: Galderma | F40: GALD SW | G40: 128.2
A41: x | D41: =+D40+1 -> 31 | E41: Viatris | F41: VTRS | G41: 8.96 | H41: =G41*[31]Main!$M$3 -> 10516.19 | I41: =[31]Main!$M$5-[31]Main!$M$6 -> -13431 | J41: =H41-I41 -> 23947.19 | K41: Q224 | L41: =+[31]Main!$M$3 -> 1173.682 | M41: 45537 | AE41: 1961
A42: x | D42: =+D41+1 -> 32 | E42: BeiGene | F42: ONC | G42: 307 | H42: =+G42*L42 -> 32142.488 | I42: =[32]Main!$L$5-[32]Main!$L$6 -> 1581.003 | J42: =H42-I42 -> 30561.485 | K42: Q224 | L42: =+[32]Main!$L$3 -> 104.69866 | M42: 45537
A43: x | D43: =+D42+1 -> 33 | E43: Astellas | F43: 4503 JP | G43: 1556.5 | H43: =+G43*L43/JPY -> 19531.133 | I43: =([33]Main!$K$5-[33]Main!$K$6)/JPY -> -5033.4527 | J43: =+H43-I43 -> 24564.586 | K43: Q224 | L43: =+[33]Main!$K$3 -> 1822.613 | M43: 45537 | AE43: 1940
A44: x | D44: =+D43+1 -> 34 | E44: Otsuka | F44: 4578 JP | G44: 7364 | H44: =+G44*L44/JPY -> 27515.54 | I44: =([34]Main!$L$5-[34]Main!$L$6)/JPY -> 6437.1704 | J44: =H44-I44 -> 21078.37 | K44: Q224 | L44: =+[34]Main!$L$3 -> 542.72573 | M44: 45539
A45: x | D45: =+D44+1 -> 35 | E45: Royalty Pharma | F45: RPRX | G45: 37.75 | H45: =+G45*L45 -> 22403.083 | I45: =+[35]Main!$L$5-[35]Main!$L$6 -> -4677.359 | J45: =+H45-I45 -> 27080.442 | K45: Q224 | L45: =+[35]Main!$L$3 -> 593.45915 | M45: 45537 | AE45: 1996
A46: x | D46: =+D45+1 -> 36 | E46: Biogen | F46: BIIB | G46: 132.15 | H46: =+G46*L46 -> 19293.9 | I46: =+[36]Main!$J$5-[36]Main!$J$6 -> -1500 | J46: =+H46-I46 -> 20793.9 | K46: Q224 | L46: =+[36]Main!$J$3 -> 146 | M46: 45721 | AE46: 1978 | AF46: Cambridge, MA
A47: x | D47: =+D55+1 -> 44 | E47: Summit | F47: SMMT | G47: 29.77 | H47: =+G47*L47 -> 21964.218 | I47: =+[37]Main!$K$5-[37]Main!$K$6 -> 412.349 | J47: =H47-I47 -> 21551.869 | K47: Q224 | L47: =+[37]Main!$K$3 -> 737.79704 | M47: 45544
A48: x | D48: =+D46+1 -> 37 | E48: Celltrion | F48: 068270 KS | G48: 173900 | H48: =+G48*L48/KRW -> 17291.351 | I48: =([38]Main!$J$5-[38]Main!$J$6)/KRW -> -768.78088 | J48: =H48-I48 -> 18060.132 | K48: Q224 | L48: =+[38]Main!$J$3 -> 142.4871 | M48: 45537
A49: x | B49: 1 | C49: 3 | D49: =+D48+1 -> 38 | E49: Grifols | F49: GRFS | G49: 10.8 | H49: =+G49*L49 -> 7425.593 | I49: =([39]Main!$L$5-[39]Main!$L$6)*EUR -> -9653.0695 | J49: =H49-I49 -> 17078.662 | K49: Q424 | L49: =+[39]Main!$L$3 -> 687.55491 | M49: 45749
A50: x | D50: =+D58+1 -> 47 | E50: Insmed | F50: INSM | G50: 112.31 | H50: =+G50*L50 -> 19300.373 | I50: =+[40]Main!$L$5-[40]Main!$L$6 -> 299.974 | J50: =+H50-I50 -> 19000.399 | K50: Q224 | L50: =+[40]Main!$L$3 -> 171.8491 | M50: 45583 | AE50: 1999
A51: x | B51: 8 | C51: 8 | D51: =+D49+1 -> 39 | E51: Biomarin | F51: BMRN | G51: 61.61 | H51: =+G51*L51 -> 12075.56 | I51: =+[41]Main!$L$5-[41]Main!$L$6 -> 1183 | J51: =H51-I51 -> 10892.56 | K51: Q125 | L51: =+[41]Main!$L$3 -> 196 | M51: 45798 | AE51: 1997 | AF51: San Rafael, CA
A52: x | D52: =+D51+1 -> 40 | E52: Genmab | F52: GMAB | G52: 22.03 | H52: =+G52*L52*10 -> 14583.253 | I52: =([42]Main!$K$7-[42]Main!$K$8)/DKK -> 0 | J52: =H52-I52 -> 14583.253 | K52: Q224 | L52: =+[42]Main!$K$4 -> 66.197244 | M52: 45537 | AE52: 1999 | AF52: Denmark
A53: x | D53: =+D52+1 -> 41 | E53: Genmab | F53: GMAB DC | G53: 1414 | H53: =+G53*L53/DKK -> 13263.838 | I53: =([42]Main!$K$7-[42]Main!$K$8)/DKK -> 0 | J53: =H53-I53 -> 13263.838 | K53: Q224 | L53: =+[42]Main!$K$4 -> 66.197244 | M53: 45537 | AE53: 1999 | AF53: Denmark
A54: x | D54: =+D53+1 -> 42 | E54: Hansoh | F54: 3692 HK | G54: 35.02 | H54: =+G54*L54/CNY -> 29306.9 | I54: =([43]Main!$J$5-[43]Main!$J$6)/CNY -> 3006.8781 | J54: =H54-I54 -> 26300.022 | K54: Q423 | L54: =+[43]Main!$J$3 -> 5933.3501 | M54: 45539 | AE54: 1995
A55: x | D55: =+D54+1 -> 43 | E55: United | F55: UTHR | G55: 295.76 | H55: =+G55*L55 -> 13158.71 | I55: =[44]Main!$K$5-[44]Main!$K$6 -> 3801.9 | J55: =H55-I55 -> 9356.8102 | K55: Q224 | L55: =+[44]Main!$K$3 -> 44.491176 | M55: 45537
A56: x | D56: =+D47+1 -> 45 | E56: Organon | F56: OGN | G56: 8.91 | H56: =+G56*L56 -> 2294.0887 | I56: =[45]Main!$L$5-[45]Main!$L$6 -> -8205 | J56: =+H56-I56 -> 10499.089 | K56: Q224 | L56: =+[45]Main!$L$3 -> 257.47348 | M56: 45562
A57: x | D57: =+D56+1 -> 46 | E57: Shanghai Fosun | F57: 600196 CH | G57: 26.84 | H57: =+G57*L57/CNY -> 10116.669 | I57: =([46]Main!$K$6-[46]Main!$K$7)/CNY -> -2662.9055 | J57: =+H57-I57 -> 12779.574 | K57: Q423 | L57: =+[46]Main!$K$4 -> 2672.3987 | M57: 45542
A58: x | D58: =+D57 -> 46 | E58: Shanghai Fosun | F58: 2196 HK | G58: 18.6 | H58: =+G58*L58/HKD -> 6372.6431 | I58: =([46]Main!$K$6-[46]Main!$K$7)/CNY -> -2662.9055 | J58: =+H58-I58 -> 9035.5486 | K58: Q423 | L58: =+[46]Main!$K$4 -> 2672.3987 | M58: 45542
A59: x | D59: =+D50+1 -> 48 | E59: Incyte | F59: INCY | G59: 78.19 | H59: =+G59*L59 -> 15059.24 | I59: =+[47]Main!$K$5-[47]Main!$K$6 -> 1549.043 | J59: =H59-I59 -> 13510.197 | K59: Q224 | L59: =+[47]Main!$K$3 -> 192.59803 | M59: 45537
A60: x | D60: =+D59+1 -> 49 | E60: Eisai | F60: 4523 JP | G60: 4304 | H60: =+G60*L60/JPY -> 8484.9519 | I60: =+([48]Main!$K$5-[48]Main!$K$6)/JPY -> 861.49398 | J60: =H60-I60 -> 7623.4579 | K60: Q224 | L60: =+[48]Main!$K$3 -> 286.34741 | M60: 45537
A61: x | D61: =+D60+1 -> 50 | E61: Jazz | F61: JAZZ | G61: 115 | H61: =+G61*L61 -> 7087.7767 | I61: =+[49]Main!$K$5-[49]Main!$K$6 -> -2795.535 | J61: =+H61-I61 -> 9883.3117 | K61: Q224 | L61: =+[49]Main!$K$3 -> 61.632841 | M61: 45537 | N61: =+[49]Model!$AP$31 -> 0 | O61: =+N61/G61-1 -> -1 | P61: =+[49]Model!$AP$28 -> 65.8225 | Q61: =+[49]Model!$AP$27 -> 36.378824 | R61: =+[49]Model!$AP$29 -> 0
A62: x | D62: =+D61+1 -> 51 | E62: Vaxcyte | F62: PCVX | G62: 33.63 | H62: =+G62*L62 -> 3753.4332 | I62: =+[50]Main!$L$5-[50]Main!$L$6 -> 1853.043 | J62: =+H62-I62 -> 1900.3902 | K62: Q224 | L62: =+[50]Main!$L$3 -> 111.60967 | M62: 45544 | AE62: 2013
A63: x | D63: =+D62+1 -> 52 | E63: Ipsen | F63: IPN | G63: 106.1 | H63: =+G63*L63*EUR -> 9870.9205 | I63: =([51]Main!$L$5-[51]Main!$L$6)*EUR -> 7.548 | J63: =+H63-I63 -> 9863.3725 | K63: Q224 | L63: =+[51]Main!$L$3 -> 83.814526 | M63: 45563
A64: x | D64: =+D63+1 -> 53 | E64: BioNTech | F64: BNTX | G64: 111.06 | H64: =+G64*L64 -> 26625.497 | I64: =+[52]Main!$K$5-[52]Main!$K$6 -> 18066.8 | J64: =+H64-I64 -> 8558.6969 | K64: Q324 | L64: =+[52]Main!$K$3 -> 239.73975 | M64: 45684 | AE64: 2008
A65: x | D65: =+D64+1 -> 54 | E65: Recordati | F65: REC IM | G65: 50.55 | H65: =G65*L65 -> 10428.423 | I65: =([53]Main!$M$5-[53]Main!$M$6)*EUR -> -1631.034 | J65: =+H65-I65 -> 12059.457 | K65: Q224 | L65: =[53]Main!$M$3 -> 206.29916 | M65: 45540 | AE65: 1926
A66: x | D66: =+D65+1 -> 55 | E66: Neurocrine | F66: NBIX | G66: 128.29 | H66: =+G66*L66 -> 13213.87 | I66: =+[54]Main!$L$5-[54]Main!$L$6 -> 1940 | J66: =H66-I66 -> 11273.87 | K66: Q424 | L66: =+[54]Main!$L$3 -> 103 | M66: 45707
A67: x | D67: =+D66+1 -> 56 | E67: Exelixis | F67: EXEL | G67: 36.72 | H67: =+G67*L67 -> 10013.848 | I67: =+[55]Main!$M$5-[55]Main!$M$6 -> 1650.757 | J67: =+H67-I67 -> 8363.091 | K67: Q125 | L67: =+[55]Main!$M$3 -> 272.70828 | M67: 45812
A68: x | D68: =+D67+1 -> 57 | E68: Halozyme | F68: HALO | G68: 60.54 | H68: =+G68*L68 -> 7669.0861 | I68: =+[56]Main!$M$5-[56]Main!$M$6 -> -973.485 | J68: =+H68-I68 -> 8642.5711 | K68: Q224 | L68: =+[56]Main!$M$3 -> 126.678 | M68: 45538
D69: =+D68+1 -> 58 | E69: Lantheus | F69: LNTH | G69: 72.03 | H69: =+G69*L69 -> 5001.0891 | I69: =+[57]Main!$K$5-[57]Main!$K$6 -> 310.253 | J69: =+H69-I69 -> 4690.8361 | K69: Q224 | L69: =+[57]Main!$K$3 -> 69.430642 | M69: 45586
A70: x | D70: =+D69+1 -> 59 | E70: Orion | F70: ORNBV FH | G70: 71.1 | H70: =+G70*L70*EUR -> 11138.436 | I70: =([58]Main!$L$5-[58]Main!$L$6)*EUR -> -123.432 | J70: =+H70-I70 -> 11261.868 | K70: Q224 | L70: =+[58]Main!$L$3 -> 141.134 | M70: 45566
A71: x | D71: =+D70+1 -> 60 | E71: Ascendis | F71: ASND | G71: 183.59 | H71: =G71*L71 -> 10690.629 | I71: =[59]Main!$K$5-[59]Main!$K$6 -> -413.639 | J71: =H71-I71 -> 11104.268 | K71: Q224 | L71: =[59]Main!$K$3 -> 58.231 | M71: 45539 | AE71: 2007 | AF71: Copenhagen, Denmark
A72: x | D72: =+D71+1 -> 61 | E72: Viking | F72: VKTX | G72: 34.05 | H72: =+G72*L72 -> 3541.2 | I72: =+[60]Main!$K$5-[60]Main!$K$6 -> 711 | J72: =+H72-I72 -> 2830.2 | K72: Q423 | L72: =+[60]Main!$K$3 -> 104 | M72: 45541
A73: x | D73: =+D72+1 -> 62 | E73: Ionis | F73: IONS | G73: 43.08 | H73: =+G73*L73 -> 6298.7738 | I73: =+[61]Main!$L$5-[61]Main!$L$6 -> 309.908 | J73: =+H73-I73 -> 5988.8658 | K73: Q224 | L73: =+[61]Main!$L$3 -> 146.21109 | M73: 45539 | AE73: 1989
A74: x | D74: =+D73+1 -> 63 | E74: Hikma | F74: HIK LN | G74: 1930 | H74: =+G74*L74/100*GBP -> 5563.6467 | I74: =+[62]Main!$K$5-[62]Main!$K$6 -> -1276 | J74: =+H74-I74 -> 6839.6467 | K74: Q224 | L74: =+[62]Main!$K$3 -> 221.74758 | M74: 45541
A75: x | D75: =+D74+1 -> 64 | E75: Kyowa Kirin | F75: 4151 JP | G75: 2565 | H75: =+G75*L75/JPY -> 9427.8622 | I75: =([63]Main!$L$5-[63]Main!$L$6)/JPY -> 2512.9707 | J75: =+H75-I75 -> 6914.8914 | K75: Q224 | L75: =+[63]Main!$L$3 -> 533.87797 | M75: 45567
A76: x | D76: =+D75+1 -> 65 | E76: Perrigo | F76: PRGO | G76: 26.7 | H76: =+G76*L76 -> 3642.2917 | I76: =+[64]Main!$N$5-[64]Main!$N$6 -> -3514.8 | J76: =+H76-I76 -> 7157.0917 | K76: Q224 | L76: =+[64]Main!$N$3 -> 136.41542 | M76: 45566
A77: x | D77: =+D76+1 -> 66 | E77: Cytokinetics | F77: CYTK | G77: 36.07 | H77: =+G77*L77 -> 4243.981 | I77: =+[65]Main!$K$5-[65]Main!$K$6 -> 707.185 | J77: =+H77-I77 -> 3536.796 | K77: Q224 | L77: =+[65]Main!$K$3 -> 117.65958 | M77: 45570
A78: x | D78: =+D77+1 -> 67 | E78: Bridgebio | F78: BBIO | G78: 47.92 | H78: =+G78*L78 -> 8989.1211 | I78: =+[66]Main!$N$5-[66]Main!$N$6 -> -1130.399 | J78: =+H78-I78 -> 10119.52 | K78: Q224 | L78: =+[66]Main!$N$3 -> 187.586 | M78: 45579
A79: x | D79: =+D78+1 -> 68 | E79: Madrigal | F79: MDGL | G79: 328 | H79: =+G79*L79 -> 7121.7581 | I79: =+[67]Main!$M$5-[67]Main!$M$6 -> 946.187 | J79: =+H79-I79 -> 6175.5711 | K79: Q224 | L79: =+[67]Main!$M$3 -> 21.712677 | M79: 45783
A80: x | D80: =+D79+1 -> 69 | E80: TG Therapeutics | F80: TGTX | G80: 27.93 | H80: =+G80*L80 -> 4324.2102 | I80: =+[68]Main!$J$5-[68]Main!$J$6 -> 115.662 | J80: =+H80-I80 -> 4208.5482 | K80: Q224 | L80: =+[68]Main!$J$3 -> 154.82314 | M80: 45580
A81: x | D81: =+D80+1 -> 70 | E81: Axsome | F81: AXSM | G81: 106 | H81: =+G81*L81 -> 5134.2274 | I81: =+[69]Main!$L$5-[69]Main!$L$6 -> 206.87 | J81: =+H81-I81 -> 4927.3574 | K81: Q224 | L81: =+[69]Main!$L$3 -> 48.436108 | M81: 45540
A82: x | D82: =+D81+1 -> 71 | E82: Legend Biotech | F82: LEGN | G82: 38.88 | H82: =+G82*L82 -> 7099.5688 | I82: =+[70]Main!$K$5-[70]Main!$K$6 -> 1008.441 | J82: =+H82-I82 -> 6091.1278 | K82: Q224 | L82: =+[70]Main!$K$3 -> 182.60208 | M82: 45574
A83: x | D83: =+D82+1 -> 72 | E83: Adma | F83: ADMA | G83: 19.86 | H83: =+G83*L83 -> 4806.12 | I83: =+[71]Main!$L$5-[71]Main!$L$6 -> -43 | J83: =+H83-I83 -> 4849.12 | K83: Q224 | L83: =+[71]Main!$L$3 -> 242 | M83: 45566
A84: x | D84: =+D83+1 -> 73 | E84: Alkermes | F84: ALKS | G84: 26.36 | H84: =+L84*G84 -> 4340.6572 | I84: =+[72]Main!$L$5-[72]Main!$L$6 -> 673.06 | J84: =+H84-I84 -> 3667.5972 | K84: Q224 | L84: =+[72]Main!$L$3 -> 164.66833 | M84: 45540
A85: x | D85: =+D84+1 -> 74 | E85: Krystal | F85: KRYS | G85: 132.99 | H85: =+G85*L85 -> 3824.8653 | I85: =+[73]Main!$K$5-[73]Main!$K$6 -> 694.212 | J85: =+H85-I85 -> 3130.6533 | K85: Q324 | L85: =+[73]Main!$K$3 -> 28.760548 | M85: 45631
A86: x | D86: =+D85+1 -> 75 | E86: Lundbeck | F86: HLUN DE | G86: 33.78 | H86: =+G86*L86/DKK -> 4747.0067 | I86: =([74]Main!$K$5-[74]Main!$K$6)/DKK -> 356.95055 | J86: =+H86-I86 -> 4390.0561 | K86: Q224 | L86: =+[74]Main!$K$3 -> 991.7 | M86: 45581
A87: x | D87: =+D86+1 -> 76 | E87: Sino Biopharm | F87: 1177 HK | G87: 7.25 | H87: =+G87*L87/HKD -> 17110.28 | I87: =([75]Main!$K$5-[75]Main!$K$6)/HKD -> 3986.4565 | J87: =H87-I87 -> 13123.824 | K87: Q224 | L87: =+[75]Main!$K$3 -> 18408.302 | M87: 45539
A88: x | D88: =+D87+1 -> 77 | E88: Alvotech | F88: ALVO | G88: 8.8 | H88: =+G88*L88 -> 2357.7362 | I88: =+[76]Main!$J$5-[76]Main!$J$6 -> -984 | J88: =+H88-I88 -> 3341.7362 | K88: Q424 | L88: =+[76]Main!$J$3 -> 267.92457 | M88: 45761
A89: x | D89: =+D88+1 -> 78 | E89: Amicus | F89: FOLD | G89: 6.93 | H89: =+G89*L89 -> 2055.3752 | I89: =+[77]Main!$M$5-[77]Main!$M$6 -> -128.877 | J89: =+H89-I89 -> 2184.2522 | K89: Q224 | L89: =+[77]Main!$M$3 -> 296.59093 | M89: 45580
A90: x | D90: =+D89+1 -> 79 | E90: Roivant | F90: ROIV | G90: 11.47 | H90: =+G90*L90 -> 8184.4123 | I90: =+[78]Main!$K$5-[78]Main!$K$6 -> 5436.548 | J90: =+H90-I90 -> 2747.8643 | K90: Q224 | L90: =+[78]Main!$K$3 -> 713.54946 | M90: 45540
A91: x | D91: =+D90+1 -> 80 | E91: Ultragenyx | F91: RARE | G91: 28.61 | H91: =+G91*L91 -> 2704.8476 | I91: =+[79]Main!$L$5-[79]Main!$L$6 -> 563.003 | J91: =+H91-I91 -> 2141.8446 | K91: Q124 | L91: =[79]Main!$L$3 -> 94.542035 | M91: 45571 | AE91: 2010
A92: x | D92: =+D91+1 -> 81 | E92: ImmunityBio | F92: IBRX | G92: 2.45 | H92: =+G92*L92 -> 1706.5069 | I92: =+[80]Main!$J$5-[80]Main!$J$6 -> -474.939 | J92: =+H92-I92 -> 2181.4459 | K92: Q224 | L92: =+[80]Main!$J$3 -> 696.53342 | M92: 45572
A93: x | D93: =+D92+1 -> 82 | E93: Apellis | F93: APLS | G93: 24.43 | H93: =G93*L93 -> 2974.7514 | I93: =+[81]Main!$L$5-[81]Main!$L$6 -> -96.747 | J93: =+H93-I93 -> 3071.4984 | K93: Q224 | L93: =[81]Main!$L$3 -> 121.76633 | M93: 45540 | AE93: 2009 | AF93: Waltham, Mass
A94: x | D94: =+D93+1 -> 83 | E94: Soleno | F94: SLNO | G94: 83.6 | H94: =+G94*L94 -> 3820.8386 | I94: =+[82]Main!$J$5-[82]Main!$J$6 -> 268.82 | J94: =+H94-I94 -> 3552.0186 | K94: Q424 | L94: =+[82]Main!$J$3 -> 45.703811 | M94: 45546 | AE94: 1999
A95: x | D95: =+D94+1 -> 84 | E95: Scholar Rock | F95: SRRK | G95: 26.93 | H95: =+G95*L95 -> 2155.2618 | I95: =+[83]Main!$K$5-[83]Main!$K$6 -> 140.421 | J95: =+H95-I95 -> 2014.8408 | K95: Q224 | L95: =+[83]Main!$K$3 -> 80.032 | M95: 45572
A96: x | D96: =+D95+1 -> 85 | E96: Arcellx | F96: ACLX | G96: 71.82 | H96: =+G96*L96 -> 3860.7329 | I96: =+[84]Main!$K$5-[84]Main!$K$6 -> 649.442 | J96: =+H96-I96 -> 3211.2909 | K96: Q224 | L96: =+[84]Main!$K$3 -> 53.755679 | M96: 45591
A97: x | D97: =+D96+1 -> 86 | E97: Amphastar | F97: AMPH | G97: 21.39 | H97: =+G97*L97 -> 1041.1758 | I97: =+[85]Main!$L$5-[85]Main!$L$6 -> -356.948 | J97: =+H97-I97 -> 1398.1238 | K97: Q224 | L97: =+[85]Main!$L$3 -> 48.675822 | M97: 45576
A98: x | D98: =+D97+1 -> 87 | E98: Edgewise | F98: EWTX | G98: 13.72 | H98: =+G98*L98 -> 1286.5558 | I98: =+[86]Main!$J$5-[86]Main!$J$6 -> 511.751 | J98: =+H98-I98 -> 774.80479 | K98: Q224 | L98: =+[86]Main!$J$3 -> 93.772288 | M98: 45554
A99: x | D99: =+D101+1 -> 89 | E99: Akero | F99: AKRO | G99: 48.93 | H99: =+G99*L99 -> 3863.4447 | I99: =+[87]Main!$L$5-[87]Main!$L$6 -> 1071.173 | J99: =+H99-I99 -> 2792.2717 | K99: Q324 | L99: =+[87]Main!$L$3 -> 78.958609 | M99: 45684
A100: x | D100: =+D99+1 -> 90 | E100: Avidity | F100: RNA | G100: 37.25 | H100: =+G100*L100 -> 4362.772 | I100: =+[88]Main!$L$5-[88]Main!$L$6 -> 1590.046 | J100: =+H100-I100 -> 2772.726 | K100: Q224 | L100: =+[88]Main!$L$3 -> 117.1214 | M100: 45558
A101: x | D101: =+D98+1 -> 88 | E101: Sarepta | F101: SRPT | G101: 16.82 | H101: =+G101*L101 -> 1631.54 | I101: =+[89]Main!$L$5-[89]Main!$L$6 -> -352 | J101: =+H101-I101 -> 1983.54 | K101: Q424 | L101: =+[89]Main!$L$3 -> 97 | M101: 45783
...

Sheet Drugs
A1: Main
B2: Brand | C2: Generic | D2: DBID | E2: Target | F2: MOA | G2: MW | H2: FDA | I2: Class | J2: AA
B3: Refludan | C3: lepirudin | D3: 1 | E3: thrombin | F3: peptide inhibitor | G3: 6979 | I3: rhProtein | J3: 65
B4: Erbitux | C4: cetuximab | D4: 2 | E4: EGFR | F4: mab | G4: 145781.6 | I4: mab
B5: Pulmozyme | C5: dornase alfa | D5: 3 | E5: extracellular DNA | F5: recombinant enzyme | G5: 29253.9 | I5: rhProtein | J5: 260
B6: Ontak | C6: denileukin difitox | D6: 4 | E6: IL-2 | F6: protein-toxin conjugate | G6: 58000 | I6: fusion protein | J6: =387+133 -> 520
B7: Enbrel | C7: etanercept | D7: 5 | E7: TNF-alpha | F7: soluble receptor | G7: 51235 | I7: rhProtein | J7: 934
B8: Angiomax | C8: bivalirudin | D8: 6 | E8: thrombin | F8: peptide inhibitor | G8: 2180 | I8: peptide | J8: 20
B9: Lupron | C9: leuprolide | D9: 7 | E9: GnRHR | F9: GnRH analog | G9: 1209 | I9: peptide | J9: 9
B10: Pegasys | C10: peginterferon alfa-2a | D10: 8 | E10: Type 1 IFNR | F10: IFNR agonist | G10: 60000 | I10: rhProtein | J10: 165
B11: Activase | C11: alteplase | D11: 9 | E11: fibrin, plasminogen | F11: recombinant enzyme | G11: 59000 | I11: rhProtein | J11: 527
B12: Geref | C12: sermorelin | D12: 10 | E12: GHRHR | F12: GRF mimetic | G12: 3358 | I12: peptide | J12: 29
B13: Wellferon | C13: interferon alfa-n1 | D13: 11 | E13: Type 1 IFNR | F13: IFNR agonist | G13: 19241 | I13: purified protein | J13: 166
B14: Aranesp | C14: darbepoetin alfa | D14: 12 | E14: EPOR | F14: EPOR agonist | G14: 18396 | I14: rhProtein
B15: Kinlytic | C15: urokinase | D15: 13 | E15: plasminogen | F15: protease | G15: 31126.5 | I15: rhProtein
B16: Zoladex | C16: goserelin | D16: 14 | E16: GnRHR | F16: LHRH analog | G16: 1269 | I16: small molecule | J16: N/A
C17: reteplase | D17: 15 | E17: plasminogen | F17: tPA analog | G17: 39589.6 | I17: rhProtein | J17: 355
B18: Procrit | C18: erythropoietin | D18: 16 | E18: EPOR | F18: EPOR agonist | G18: 18396 | I18: rhProtein | J18: 165
C19: salmon calcitonin | D19: 17 | E19: Calcitonin receptor | F19: calcitonin receptor agonist | G19: 3431.853 | I19: peptide | J19: 32
C20: interferon alfa-n3 | D20: 18 | E20: Type 1 IFNR | F20: IFNR agonist | I20: purified protein | J20: 166
B21: Neulasta | C21: pegfilgrastim | D21: 19 | E21: G-CSF Receptor | F21: G-CSF | G21: 39000 | I21: rhProtein
B22: Leukine | C22: sargramostim | D22: 20 | E22: GM-CSF-R-alpha | F22: GM-CSF | G22: 14434.5 | I22: rhProtein | J22: 127
C23: secretin | D23: 21 | E23: secretin receptor | F23: secretin receptor agonist | G23: 3039 | I23: peptide | J23: 27
C24: peginterferon alfa-2b | D24: 22 | E24: Type 1 IFNR | F24: IFNR agonist | G24: 31000 | I24: rhProtein
B25: Rylaze | C25: asparginase | D25: 23 | E25: L-asparagine | F25: recombinant enzyme
B26: Thyrogen | C26: thyrotropin alfa | D26: 24 | E26: TSH receptor | F26: TSH receptor agonist | G26: 22673 | I26: rhProtein
B27: Advate | C27: antihemophilic factor | D27: 25 | E27: Factor IXa | F27: Factor IXa complex component | G27: 264726 | I27: rhProtein | J27: 2332
B28: Kineret | C28: anakinra | D28: 26 | E28: IL-1 | F28: soluble receptor | G28: 17257.6 | I28: rhProtein | J28: 153
C29: gramicidin D | D29: 27 | G29: 1811.253 | I29: peptide | J29: 15
B30: Gammagard | C30: human immunoglobulin G | D30: 28 | G30: 142682.3 | I30: purified protein
C31: anistreplase | D31: 29 | E31: plasminogen | F31: recombinant enzyme | G31: 59042.3 | I31: rhProtein | J31: 527
B32: Humulin | C32: insulin human | D32: 30 | E32: Insulin Receptor | F32: insulin receptor agonist | G32: 5808 | I32: rhProtein | J32: 51
B33: TNKase | C33: tenecteplase | D33: 31 | E33: plasminogen | F33: tPA analog | G33: 58951.2 | I33: rhProtein | J33: 527
B34: Menopur | C34: menotropins | D34: 32 | E34: FSH receptor | F34: FSH agonist | G34: 23390.3 | I34: purified protein
B35: Actimmune | C35: interferon gamma-1b | D35: 33 | E35: Type 1 IFNR | F35: IFNR agonist | G35: 17145.6 | I35: rhProtein | J35: 140
C36: interferon alfa-2a | D36: 34 | E36: Type 1 IFNR | F36: IFNR agonist | G36: 19241.1 | I36: rhProtein | J36: 165
B37: Ddavp | C37: desmopressin | D37: 35 | E37: V1, V2, V3 receptors | F37: vasopressin receptor agonist | G37: 1069 | I37: peptide | J37: 8
B38: NovoSeven | C38: coagulation factor VIIa recombinant human | D38: 36 | E38: Factor IX, Factor X | F38: recombinant enzyme | G38: 45079
C39: interferon alfa-2a | D39: 37 | E39: Type 1 IFNR | F39: IFNR agonist | G39: 19241.1 | I39: rhProtein | J39: 165
B40: Neumega | C40: oprelvekin | D40: 38 | E40: IL-11 receptor | F40: IL-11 receptor agonist | G40: 19047 | I40: rhProtein | J40: 177
B41: Kepivance | C41: palifermin | D41: 39 | E41: KGF receptor | F41: KGF receptor agonist | G41: 16192.7 | I41: rhProtein | J41: 140
B42: Glucagen | C42: glucagon | D42: 40 | E42: Glucagon receptor | F42: Glucagon receptor agonist | G42: 3767.1 | I42: peptide | J42: 29
B43: Proleukin | C43: aldesleukin | D43: 41 | E43: IL-2 receptor | F43: IL-2 receptor agonist | G43: 15314.8 | I43: rhProtein | J43: 12
B44: Myobloc | C44: botulinum toxin type B | D44: 42 | G44: 150804
B45: Xolair | C45: omalizumab | D45: 43 | E45: IgE | F45: mab | G45: 149000 | I45: mab
C46: lutropin alfa | D46: 44 | E46: LH receptor | F46: LH receptor agonist | G46: 30000 | I46: rhProtein
C47: lyme disease vaccine | D47: 45 | G47: 27743
B48: Humalog | C48: insulin lispro | D48: 46 | E48: Insulin Receptor | F48: insulin receptor agonist | G48: 5808 | I48: rhProtein | J48: 51
B49: Lantus | C49: insulin glargine | D49: 47 | E49: Insulin Receptor | F49: insulin receptor agonist | G49: 6063 | I49: rhProtein
B50: Xiaflex | C50: collagenase clostridium histolyticum | D50: 48 | F50: recombinant enzyme
B51: Elitek | C51: rasburicase | D51: 49 | G51: 34109.5
C52: cetrorelix | D52: 50 | E52: GnRHR | F52: GnRH analog | G52: 1431 | I52: peptide | J52: 10
B53: Humira | C53: adalimumab | D53: 51 | E53: TNF-alpha | F53: mab | G53: 144190 | I53: mab
B54: Genotropin | C54: somatotropin | D54: 52 | E54: Growth Hormone receptor | F54: GH receptor agonist | G54: 22129 | I54: rhProtein
B55: Cerezyme | C55: imiglucerase | D55: 53 | F55: recombinant enzyme | G55: 55597.4 | I55: rhProtein | J55: 497
C56: abciximab | D56: 54 | F56: mab | G56: 145651 | I56: mab
B57: Cosentyx | C57: secukinumab | D57: 9029 | E57: IL-17A | F57: mab | I57: mab
C58: secretin | D58: 9532 | E58: secretin receptor | F58: secretin receptor agonist | G58: 3039 | I58: peptide | J58: 27

Sheet Industry Model
A1: Main
C2: Q123 | D2: Q223 | E2: Q323 | F2: Q423 | G2: Q124 | H2: Q224 | I2: Q324 | J2: Q424 | M2: 2023 | N2: 2024
B3: J&J | G3: 21382 | H3: 22453
B4: Merck | G4: 15775 | H4: 16112
B5: AbbVie | G5: 12310 | H5: 14462
B6: Lilly | G6: 8768 | H6: 11303
B7: Novo | G7: =65349/DKK -> 9260.1672 | H7: =68060/DKK -> 9644.3248
B8: Revenue | C8: =SUM(C3:C7) -> 0 | D8: =SUM(D3:D7) -> 0 | E8: =SUM(E3:E7) -> 0 | F8: =SUM(F3:F7) -> 0 | G8: =SUM(G3:G7) -> 67495.167 | H8: =SUM(H3:H7) -> 73974.325
B9: Lilly COGS | G9: 1534.4 | H9: 2031.1
B10: J&J COGS | G10: 5404 | H10: 6869
B11: AbbVie COGS | G11: 2108 | H11: 2135
B12: Merck COGS | G12: 2961 | H12: 3073
B13: Novo COGS | G13: =9916/DKK -> 1405.1297 | H13: =10274/DKK -> 1455.8594
B14: COGS | G14: =SUM(G9:G13) -> 13412.53 | H14: =SUM(H9:H13) -> 15563.959
B15: Gross Margin | G15: =+G8-G14 -> 54082.638 | H15: =+H8-H14 -> 58410.365
B16: R&D | N16: =SUM(N17:N21) -> 53959.552
B17: Lilly R&D | N17: 9998
B18: AbbVie R&D | N18: 7795
B19: Novo R&D | N19: =45766/7.25 -> 6312.5517
B20: Pfizer R&D | M20: 11988 | N20: 11988
B21: Merck R&D | N21: 17866
B22: Novartis R&D | N22: 9214
B23: J&J R&D
B24: Sanofi R&D
B25: GSK R&D
B26: Amgen R&D
B31: Industry GM% | C31: =+C15/C8 -> #DIV/0! | D31: =+D15/D8 -> #DIV/0! | G31: =+G15/G8 -> 0.80128163 | H31: =+H15/H8 -> 0.78960322

Sheet Todo
B2: ORGO - look at new product for OA
B3: DCTH - assess revenue potential, look at dilutive instruments
B4: QXO - study Brad Jacobs
B5: SAVA - continue
B6: HIMS - listen to conference calls
B7: ABCL - deeper dive
B8: SQ - listen to conference calls, check if new product/pipeline disclosed
B9: JBL - listen to conference calls, model more years, do forecasts, look into customers, compare to macroeconomic data
B10: PCVX - deeper dive, conf calls, patents
B11: SYM - keep an eye on it
B12: CTAS
B13: ACET
... B23: TRVI - dig deeper

Sheet Launches
A1: Main | AN1: =AVERAGE(AN3:AN4,AN6:AN34,AN36:AN52) -> 291.80038
A2: # | B2: Drug | C2: Company | D2: Indication | E2: # in Class | F2: Launch | G2: Lifetime | I2: Y1 | J2: Y2 | K2: Y3 | L2: Y4 | M2: Y5 | N2: Y6 | O2: Y7 | P2: Y8 | Q2: Y9 | R2: Y10 | S2: Y11 | T2: Y12 | U2: Y13 | V2: Y14 | W2: Y15 | X2: Y16 | Y2: Y17 | Z2: Y18 | AA2: Y19 | AB2: Y20 | AC2: Y21 | AD2: Y22 | AE2: Y23 | AF2: Y24 | AG2: Y25 | AH2: Y26 | AK2: Q1 | AL2: Q2 | AM2: Q3 | AN2: Q4 | AO2: Q5 | AP2: Q6 | AQ2: Q7 | AR2: Q8 | AS2: Q9 | AT2: Q10 | AU2: Q11 | AV2: Q12 | AW2: Q13 | AX2: Q14 | AY2: Q15 | AZ2: Q16 | BA2: Q17 | BB2: Q18 | BC2: Q19 | BD2: Q20 | BE2: Q21 | BF2: Q22 | BG2: Q23 | BH2: Q24 | BI2: Q25 | BJ2: Q26 | BK2: Q27 | BL2: Q28 | BM2: Q29
A3: 1 | B3: Humira | C3: ABBV | D3: Autoimmune | E3: 3 | F3: Q103 | G3: =SUM(AK3:GH3) -> 233470 | I3: =SUM(AK3:AN3) -> 280 | J3: =SUM(AO3:AR3) -> 852 | K3: =SUM(AS3:AV3) -> 1400 | L3: =SUM(AW3:AZ3) -> 2044 | M3: =SUM(BA3:BD3) -> 3063 | N3: =SUM(BE3:BH3) -> 4522 | O3: =SUM(BI3:BL3) -> 5488 | P3: =SUM(BM3:BP3) -> 6548 | Q3: =SUM(BQ3:BT3) -> 7932 | R3: =SUM(BU3:BX3) -> 9266 | S3: =SUM(BY3:CB3) -> 10659 | T3: =SUM(CC3:CF3) -> 12543 | U3: =SUM(CG3:CJ3) -> 14012 | V3: =SUM(CK3:CN3) -> 16078 | W3: =SUM(CO3:CR3) -> 18427 | X3: =SUM(CS3:CV3) -> 19936 | AK3: 30 | AL3: 60 | AM3: 80 | AN3: 110 | AO3: 149 | AP3: 203 | AQ3: 227 | AR3: 273 | AS3: 282 | AT3: 321 | AU3: 356 | AV3: 441 | AW3: 392 | AX3: 491 | AY3: 541 | AZ3: 620 | BA3: 571 | BB3: 735 | BC3: 803 | BD3: 954 | BE3: 878 | BF3: 1089 | BG3: 1204 | BH3: 1351 | BI3: 1024 | BJ3: 1311 | BK3: 1491 | BL3: 1662 | BM3: 1397 | BN3: 1593 | BO3: 1679 | BP3: 1879 | BQ3: 1646 | BR3: 1997 | BS3: 2111 | BT3: 2178 | BU3: 1934 | BV3: 2326 | BW3: 2325 | BX3: 2681 | BY3: 2244 | BZ3: 2606 | CA3: 2770 | CB3: 3039 | CC3: 2637 | CD3: 3288 | CE3: 3255 | CF3: 3363 | CG3: 3111 | CH3: 3537 | CI3: 3647 | CJ3: 3717 | CK3: 3577 | CL3: 4149 | CM3: 4060 | CN3: 4292 | CO3: 4118 | CP3: 4716 | CQ3: 4701 | CR3: 4892 | CS3: 4709 | CT3: 5185 | CU3: 5124 | CV3: 4918 | CW3: 4446 | CX3: 4870 | CY3: 4936 | CZ3: 4917 | DA3: 4703 | DB3: 4837 | DC3: 5140 | DD3: 5152 | DE3: 4867 | DF3: 5068 | DG3: 5425 | DH3: 5334 | DI3: 4736 | DJ3: 5363 | DK3: 5559 | DL3: 5579 | DM3: 3541 | DN3: 4012 | DO3: 3547 | DP3: 3304 | DQ3: 2270 | DR3: 2814
A4: =+A12+1 -> 4 | B4: Remicade US | C4: JNJ | D4: Autoimmune | E4: 1 | G4: =SUM(AK4:GH4) -> 92404 | I4: =SUM(AK4:AN4) -> 115 | J4: =SUM(AO4:AR4) -> 370 | K4: =SUM(AS4:AV4) -> 721 | L4: =SUM(AW4:AZ4) -> 1297 | M4: =SUM(BA4:BD4) -> 1730 | N4: =SUM(BE4:BH4) -> 2146 | O4: =SUM(BI4:BL4) -> 2535 | P4: =SUM(BM4:BP4) -> 3014 | Q4: =SUM(BQ4:BT4) -> 3327 | R4: =SUM(BU4:BX4) -> 3748 | S4: =SUM(BY4:CB4) -> 4304 | T4: =SUM(CC4:CF4) -> 4610 | U4: =SUM(CG4:CJ4) -> 5492 | V4: =SUM(CK4:CN4) -> 6139 | AK4: 21 | AL4: 26 | AM4: 27 | AN4: 41 | AO4: 49 | AP4: 91.2 | AQ4: 90.8 | AR4: 139 | AS4: 131 | AT4: 171 | AU4: 209 | AV4: 210 | AW4: 245 | AX4: 332 | AY4: 341 | AZ4: 379 | BA4: 409 | BB4: 421 | BC4: 444 | BD4: 456 | BE4: 464 | BF4: 539 | BG4: 545 | BH4: 598 | BI4: 577 | BJ4: 642 | BK4: 624 | BL4: 692 | BM4: 681 | BN4: 777 | BO4: 776 | BP4: 780 | BQ4: 731 | BR4: 869 | BS4: 819 | BT4: 908 | BU4: 998 | BV4: 886 | BW4: 978 | BX4: 886 | BY4: 1028 | BZ4: 1102 | CA4: 1036 | CB4: 1138 | CC4: 1186 | CD4: 1130 | CE4: 1229 | CF4: 1065 | CG4: 1285 | CH4: 1371 | CI4: 1408 | CJ4: 1428 | CK4: 1521 | CL4: 1523 | CM4: 1591 | CN4: 1504 | CO4: 1600 | CP4: 1672 | CQ4: 1689 | CR4: 1712 | CS4: 1610 | CT4: 1804 | CU4: 1782 | CV4: 1672 | CW4: 1600 | CX4: 1668 | CY4: 1613 | CZ4: 1680 | DA4: 1779 | DB4: 1780 | DC4: 1783 | DD4: 1624 | DE4: 1672 | DF4: 1530 | DG4: 1647 | DH4: 1466 | DI4: 1389 | DJ4: 1320 | DK4: 1379 | DL4: 1238 | DM4: 1102 | DN4: 1107 | DO4: 1136 | DP4: 1035 | DQ4: 990 | DR4: 935 | DS4: 921 | DT4: 901 | DU4: 777 | DV4: 888 | DW4: 761 | DX4: 764 | DY4: 663 | DZ4: 647 | EA4: 558 | EB4: 475 | EC4: 487
A5: =+A4+1 -> 5 | B5: Comirnaty | C5: PFE | D5: Vaccine | G5: =SUM(AK5:GH5) -> 86510 | I5: =SUM(AK5:AN5) -> 24431 | J5: =SUM(AO5:AR5) -> 38981 | K5: =SUM(AS5:AV5) -> 17188 | L5: =SUM(AW5:AZ5) -> 5910 | M5: =SUM(BA5:BD5) -> 0 | N5: =SUM(BE5:BH5) -> 0 | O5: =SUM(BI5:BL5) -> 0 | P5: =SUM(BM5:BP5) -> 0 | Q5: =SUM(BQ5:BT5) -> 0 | R5: =SUM(BU5:BX5) -> 0 | S5: =SUM(BY5:CB5) -> 0 | T5: =SUM(CC5:CF5) -> 0 | U5: =SUM(CG5:CJ5) -> 0 | V5: =SUM(CK5:CN5) -> 0 | AK5: 154 | AL5: 3462 | AM5: 7838 | AN5: 12977 | AO5: 12504 | AP5: 13227 | AQ5: 8848 | AR5: 4402 | AS5: 11329 | AT5: 3064 | AU5: 1488 | AV5: 1307 | AW5: 5361 | AX5: 354 | AY5: 195
A6: =+A8+1 -> 10 | B6: Biktarvy | C6: GILD | D6: HIV | G6: =SUM(AK6:GH6) -> 50224 | I6: =SUM(AK6:AN6) -> 1184 | J6: =SUM(AO6:AR6) -> 4738 | K6: =SUM(AS6:AV6) -> 7259 | L6: =SUM(AW6:AZ6) -> 8624 | M6: =SUM(BA6:BD6) -> 10391 | N6: =SUM(BE6:BH6) -> 11850 | O6: =SUM(BI6:BL6) -> 6178 | P6: =SUM(BM6:BP6) -> 0 | Q6: =SUM(BQ6:BT6) -> 0 | R6: =SUM(BU6:BX6) -> 0 | S6: =SUM(BY6:CB6) -> 0 | T6: =SUM(CC6:CF6) -> 0 | U6: =SUM(CG6:CJ6) -> 0 | V6: =SUM(CK6:CN6) -> 0 | AK6: 35 | AL6: 185 | AM6: 386 | AN6: 578 | AO6: 793 | AP6: 1116 | AQ6: 1259 | AR6: 1570 | AS6: 1693 | AT6: 1604 | AU6: 1891 | AV6: 2071 | AW6: 1824 | AX6: 1994 | AY6: 2276 | AZ6: 2530 | BA6: 2151 | BB6: 2556 | BC6: 2766 | BD6: 2918 | BE6: 2677 | BF6: 2979 | BG6: 3085 | BH6: 3109 | BI6: 2946 | BJ6: 3232
A7: =+A11+1 -> 19 | B7: Harvony | C7: GILD | D7: HCV | G7: =SUM(AK7:GH7) -> 31975 | I7: =SUM(AK7:AN7) -> 9314 | J7: =SUM(AO7:AR7) -> 12258 | K7: =SUM(AS7:AV7) -> 6253 | L7: =SUM(AW7:AZ7) -> 2296 | M7: =SUM(BA7:BD7) -> 961 | N7: =SUM(BE7:BH7) -> 404 | O7: =SUM(BI7:BL7) -> 211 | P7: =SUM(BM7:BP7) -> 152 | Q7: =SUM(BQ7:BT7) -> 86 | R7: =SUM(BU7:BX7) -> 40 | S7: =SUM(BY7:CB7) -> 0 | T7: =SUM(CC7:CF7) -> 0 | U7: =SUM(CG7:CJ7) -> 0 | V7: =SUM(CK7:CN7) -> 0 | AK7: 20 | AL7: 2107 | AM7: 3579 | AN7: 3608 | AO7: 3332 | AP7: 3345 | AQ7: 3017 | AR7: 2564 | AS7: 1860 | AT7: 1640 | AU7: 1371 | AV7: 1382 | AW7: 973 | AX7: 644 | AY7: 348 | AZ7: 331 | BA7: 311 | BB7: 232 | BC7: 225 | BD7: 193 | BE7: 124 | BF7: 101 | BG7: 112 | BH7: 67 | BI7: 84 | BJ7: 9 | BK7: 56 | BL7: 62 | BM7: 45 | BN7: 49 | BO7: 35 | BP7: 23 | BQ7: 25 | BR7: 31 | BS7: 15 | BT7: 15 | BU7: 23 | BV7: 17
A8: =+A16+1 -> 9 | B8: Opdivo | C8: BMY | D8: Oncology | E8: 1 | G8: =SUM(AK8:GH8) -> 59847 | I8: 942 | J8: 3774 | K8: 4948 | L8: 6735 | M8: 7204 | N8: 6992 | O8: 7523 | P8: =SUM(BM8:BP8) -> 7879 | Q8: =SUM(BQ8:BT8) -> 8610 | R8: =SUM(BU8:BX8) -> 9127 | S8: =SUM(BY8:CB8) -> 0 | T8: =SUM(CC8:CF8) -> 0 | U8: =SUM(CG8:CJ8) -> 0 | V8: =SUM(CK8:CN8) -> 0 | AK8: 1 | AL8: 5 | AM8: 40 | AN8: 122 | AO8: 305 | AP8: 475 | AQ8: 704 | AR8: 840 | AS8: 920 | AT8: 1310 | AU8: 1127 | AV8: 1195 | AW8: 1265 | AX8: 1361 | AY8: 1511 | AZ8: 1627 | BA8: 1793 | BB8: 1804 | BC8: 1801 | BD8: 1823 | BE8: 1817 | BF8: 1763 | BG8: 1766 | BH8: 1653 | BI8: 1780 | BJ8: 1793 | BK8: 1720 | BL8: 1910 | BM8: 1905 | BN8: 1988 | BO8: 1923 | BP8: 2063 | BQ8: 2047 | BR8: 2216 | BS8: 2202 | BT8: 2145 | BU8: 2275 | BV8: 2387 | BW8: 2078 | BX8: 2387
A9: =+A33+1 -> 23 | B9: Genvoya | C9: GILD | D9: HIV | G9: =SUM(AK9:GH9) -> 25283 | I9: =SUM(AK9:AN9) -> 966 | J9: =SUM(AO9:AR9) -> 3177 | K9: =SUM(AS9:AV9) -> 4478 | L9: =SUM(AW9:AZ9) -> 4179 | M9: =SUM(BA9:BD9) -> 3444 | N9: =SUM(BE9:BH9) -> 2975 | O9: =SUM(BI9:BL9) -> 2520 | P9: =SUM(BM9:BP9) -> 2184 | Q9: =SUM(BQ9:BT9) -> 1360 | R9: =SUM(BU9:BX9) -> 0 | S9: =SUM(BY9:CB9) -> 0 | T9: =SUM(CC9:CF9) -> 0 | U9: =SUM(CG9:CJ9) -> 0 | V9: =SUM(CK9:CN9) -> 0 | AK9: 45 | AL9: 158 | AM9: 302 | AN9: 461 | AO9: 563 | AP9: 769 | AQ9: 857 | AR9: 988 | AS9: 1060 | AT9: 1082 | AU9: 1160 | AV9: 1176 | AW9: 1206 | AX9: 1015 | AY9: 980 | AZ9: 978 | BA9: 958 | BB9: 824 | BC9: 816 | BD9: 846 | BE9: 852 | BF9: 673 | BG9: 706 | BH9: 744 | BI9: 756 | BJ9: 582 | BK9: 582 | BL9: 600 | BM9: 640 | BN9: 501 | BO9: 540 | BP9: 503 | BQ9: 517 | BR9: 403 | BS9: 440
A10: 2 | B10: Lipitor | C10: PFE | D10: Cardiovascular | F10: Q197 | G10: =SUM(AK10:GH10) -> 146735 | I10: =SUM(AK10:AN10) -> 865 | J10: =SUM(AO10:AR10) -> 2208 | K10: =SUM(AS10:AV10) -> 3796 | L10: =SUM(AW10:AZ10) -> 5031 | M10: =SUM(BA10:BD10) -> 6449 | N10: =SUM(BE10:BH10) -> 7972 | O10: =SUM(BI10:BL10) -> 9230 | P10: =SUM(BM10:BP10) -> 10862 | Q10: =SUM(BQ10:BT10) -> 12187 | R10: =SUM(BU10:BX10) -> 12886 | S10: =SUM(BY10:CB10) -> 12675 | T10: =SUM(CC10:CF10) -> 12401 | U10: =SUM(CG10:CJ10) -> 11434 | V10: =SUM(CK10:CN10) -> 10733 | W10: =SUM(CO10:CR10) -> 9577 | X10: =SUM(CS10:CV10) -> 3948 | AK10: 49 | AL10: 151 | AM10: 257 | AN10: 408 | AO10: 375 | AP10: 536 | AQ10: 578 | AR10: 719 | AS10: 767 | AT10: 900 | AU10: 995 | AV10: 1134 | AW10: 1119 | AX10: 1262 | AY10: 1216 | AZ10: 1434 | BA10: 1467 | BB10: 1439 | BC10: 1660 | BD10: 1883 | BE10: 1852 | BF10: 1783 | BG10: 2020 | BH10: 2317 | BI10: 2099 | BJ10: 2015 | BK10: 2468 | BL10: 2648 | BM10: 2497 | BN10: 2363 | BO10: 2738 | BP10: 3264 | BQ10: 3075 | BR10: 2858 | BS10: 2897 | BT10: 3357 | BU10: 3107 | BV10: 3123 | BW10: 3321 | BX10: 3335 | BY10: 3358 | BZ10: 2719 | CA10: 3170 | CB10: 3428 | CC10: 3137 | CD10: 2976 | CE10: 3142 | CF10: 3146 | CG10: 2721 | CH10: 2685 | CI10: 2853 | CJ10: 3175 | CK10: 2757 | CL10: 2813 | CM10: 2534 | CN10: 2629 | CO10: 2385 | CP10: 2591 | CQ10: 2602 | CR10: 1999 | CS10: 1395 | CT10: 1220 | CU10: 749 | CV10: 584 | CW10: 626 | CX10: 545 | CY10: 533 | CZ10: 611 | DA10: 457 | DB10: 543 | DC10: 490 | DD10: 572 | DE10: 441 | DF10: 509 | DG10: 454 | DH10: 456 | DI10: 411 | DJ10: 461 | DK10: 422 | DL10: 464 | DM10: 404 | DN10: 445 | DO10: 491 | DP10: 574 | DQ10: 511 | DR10: 521 | DS10: 507 | DT10: 524 | DU10: 622 | DV10: 107 | DW10: 476 | DX10: 468 | DY10: 405 | DZ10: 431
A11: =+A30+1 -> 18 | B11: Ozempic | C11: NOVO | D11: Diabetes | G11: =SUM(AK11:GH11) -> 32529.592 | I11: =SUM(AK11:AN11) -> 769.97085 | J11: =SUM(AO11:AR11) -> 2489.5044 | K11: =SUM(AS11:AV11) -> 3748.8338 | L11: =SUM(AW11:AZ11) -> 6704.3732 | M11: =SUM(BA11:BD11) -> 10948.542 | N11: =SUM(BE11:BH11) -> 7868.3673 | O11: =SUM(BI11:BL11) -> 0 | P11: =SUM(BM11:BP11) -> 0 | Q11: =SUM(BQ11:BT11) -> 0 | R11: =SUM(BU11:BX11) -> 0 | S11: =SUM(BY11:CB11) -> 0 | T11: =SUM(CC11:CF11) -> 0 | U11: =SUM(CG11:CJ11) -> 0 | V11: =SUM(CK11:CN11) -> 0 | AK11: =540/$C$71 -> 78.717201 | AL11: =992/$C$71 -> 144.60641 | AM11: =1425/$C$71 -> 207.72595 | AN11: =2325/$C$71 -> 338.92128 | AO11: =3122/$C$71 -> 455.10204 | AP11: =4365/$C$71 -> 636.29738 | AQ11: =4755/$C$71 -> 693.14869 | AR11: =4836/$C$71 -> 704.95627 | AS11: =5432/$C$71 -> 791.83673 | AT11: =6188/$C$71 -> 902.04082 | AU11: =6662/$C$71 -> 971.13703 | AV11: =7435/$C$71 -> 1083.8192 | AW11: =8892/$C$71 -> 1296.2099 | AX11: =10716/$C$71 -> 1562.0991 | AY11: =12035/$C$71 -> 1754.3732 | AZ11: =14349/$C$71 -> 2091.691 | BA11: =16390/$C$71 -> 2389.2128 | BB11: =16976/$C$71 -> 2474.6356 | BC11: =19640/$C$71 -> 2862.9738 | BD11: =22101/C71 -> 3221.7201 | BE11: =23912/C71 -> 3485.7143 | BF11: =30065/C71 -> 4382.6531
A12: 3 | B12: Eliquis WW | C12: PFE/BMY | D12: Cardiovascular | E12: 2 | F12: Q113 | G12: =+G78+G79 -> 118779 | I12: =+I78+I79 -> 412 | J12: =+J78+J79 -> 1562 | K12: =+K78+K79 -> 3260 | L12: =+L78+L79 -> 5005 | M12: =+M78+M79 -> 7395 | N12: =+N78+N79 -> 9872 | O12: =+O78+O79 -> 12149 | P12: =+P78+P79 -> 13881 | ... V12: =+V78+V79 -> 0
A13: =+A27+1 -> 14 | B13: Ibrance | C13: PFE | D13: Oncology | E13: 1 | G13: =SUM(AK13:GH13) -> 37946 | I13: =SUM(AK13:AN13) -> 723 | J13: =SUM(AO13:AR13) -> 2136 | K13: =SUM(AS13:AV13) -> 3126 | L13: =SUM(AW13:AZ13) -> 4118 | M13: =SUM(BA13:BD13) -> 4960 | N13: =SUM(BE13:BH13) -> 5390 | O13: =SUM(BI13:BL13) -> 5437 | P13: =SUM(BM13:BP13) -> 5119 | Q13: =SUM(BQ13:BT13) -> 4753 | R13: =SUM(BU13:BX13) -> 2184 | S13: =SUM(BY13:CB13) -> 0 | T13: =SUM(CC13:CF13) -> 0 | U13: =SUM(CG13:CJ13) -> 0 | V13: =SUM(CK13:CN13) -> 0 | AK13: 38 | AL13: 140 | AM13: 230 | AN13: 315 | AO13: 429 | AP13: 514 | AQ13: 550 | AR13: 643 | AS13: 679 | AT13: 853 | AU13: 878 | AV13: 716 | AW13: 933 | AX13: 1027 | AY13: 1025 | AZ13: 1133 | BA13: 1133 | BB13: 1261 | BC13: 1283 | BD13: 1283 | BE13: 1248 | BF13: 1349 | BG13: 1357 | BH13: 1436 | BI13: 1254 | BJ13: 1404 | BK13: 1381 | BL13: 1398 | BM13: 1237 | BN13: 1320 | BO13: 1283 | BP13: 1279 | BQ13: 1144 | BR13: 1247 | BS13: 1244 | BT13: 1118 | BU13: 1054 | BV13: 1130
A14: 2 | B14: Keytruda | C14: MRK | D14: Oncology | E14: 2 | F14: Q314 | G14: =SUM(AK14:GH14) -> 123247 | I14: =SUM(AK14:AN14) -> 247 | J14: =SUM(AO14:AR14) -> 936 | K14: =SUM(AS14:AV14) -> 2304 | L14: =SUM(AW14:AZ14) -> 5475 | M14: =SUM(BA14:BD14) -> 8943 | N14: =SUM(BE14:BH14) -> 12853 | O14: =SUM(BI14:BL14) -> 15783 | P14: =SUM(BM14:BP14) -> 19172 | Q14: =SUM(BQ14:BT14) -> 22942 | R14: =SUM(BU14:BX14) -> 27163 | S14: =SUM(BY14:CB14) -> 7429 | T14: =SUM(CC14:CF14) -> 0 | U14: =SUM(CG14:CJ14) -> 0 | V14: =SUM(CK14:CN14) -> 0 | AK14: 4 | AL14: 50 | AM14: 83 | AN14: 110 | AO14: 159 | AP14: 214 | AQ14: 249 | AR14: 314 | AS14: 356 | AT14: 483 | AU14: 584 | AV14: 881 | AW14: 1047 | AX14: 1297 | AY14: 1464 | AZ14: 1667 | BA14: 1889 | BB14: 2151 | BC14: 2269 | BD14: 2634 | BE14: 3070 | BF14: 3111 | BG14: 3284 | BH14: 3388 | BI14: 3715 | BJ14: 3993 | BK14: 3899 | BL14: 4176 | BM14: 4534 | BN14: 4577 | BO14: 4809 | BP14: 5252 | BQ14: 5426 | BR14: 5450 | BS14: 5795 | BT14: 6271 | BU14: 6338 | BV14: 6608 | BW14: 6947 | BX14: 7270 | BY14: 7429
A15: =+A32+1 -> 7 | B15: Januvia+Janumet | C15: MRK | D15: Diabetes | E15: 1 | G15: =SUM(AK15:GH15) -> 74776.5 | I15: =SUM(AK15:AN15) -> 589 | J15: =SUM(AO15:AR15) -> 1600.5 | K15: =SUM(AS15:AV15) -> 2095 | L15: =SUM(AW15:AZ15) -> 3327 | M15: =SUM(BA15:BD15) -> 4488 | N15: =SUM(BE15:BH15) -> 5589 | O15: =SUM(BI15:BL15) -> 5912 | P15: =SUM(BM15:BP15) -> 6073 | Q15: =SUM(BQ15:BT15) -> 6172 | R15: =SUM(BU15:BX15) -> 6087 | S15: =SUM(BY15:CB15) -> 5937 | T15: =SUM(CC15:CF15) -> 5907 | U15: =SUM(CG15:CJ15) -> 5483 | V15: =SUM(CK15:CN15) -> 5346 | AK15: =AK80+AK81 -> 66 | AL15: =AL80+AL81 -> 106 | AM15: =AM80+AM81 -> 174 | AN15: =AN80+AN81 -> 243 | AO15: =AO80+AO81 -> 272 | AP15: =AP80+AP81 -> 373 | AQ15: =AQ80+AQ81 -> 448.5 | AR15: =AR80+AR81 -> 507 | ... CZ15: =CZ80+CZ81 -> 0
A16: =+A15+1 -> 8 | B16: Zyprexa | C16: LLY | D16: Psychiatry | G16: =SUM(AK16:GH16) -> 63086.7 | I16: =SUM(AK16:AN16) -> 550.2 | J16: =SUM(AO16:AR16) -> 1278 | K16: =SUM(AS16:AV16) -> 1726.1 | L16: =SUM(AW16:AZ16) -> 2246.6 | M16: =SUM(BA16:BD16) -> 2882.4 | N16: =SUM(BE16:BH16) -> 3604.1 | O16: =SUM(BI16:BL16) -> 4128.1 | P16: =SUM(BM16:BP16) -> 4479.8 | Q16: =SUM(BQ16:BT16) -> 4255.6 | R16: =SUM(BU16:BX16) -> 4239.3 | S16: =SUM(BY16:CB16) -> 4643.6 | T16: =SUM(CC16:CF16) -> 4823.3 | U16: =SUM(CG16:CJ16) -> 4695.9 | V16: =SUM(CK16:CN16) -> 5057.1 | AK16: 87 | AL16: 105.4 | AM16: 156 | AN16: 201.8 | AO16: 267 | AP16: 287 | AQ16: 328 | AR16: 396 | AS16: 429 | AT16: 401.2 | AU16: 393 | AV16: 502.9 | AW16: 592.9 | AX16: 458.1 | AY16: 550.7 | AZ16: 644.9 | BA16: 696.3 | BB16: 637 | BC16: 736.6 | BD16: 812.5 | BE16: 903.9 | BF16: 819.4 | BG16: 906.8 | BH16: 974 | BI16: 989.8 | BJ16: 958.3 | BK16: 1050 | BL16: 1130 | BM16: 1145.5 | BN16: 1098.3 | BO16: 1212.3 | BP16: 1023.7 | BQ16: 1085.5 | BR16: 1038.2 | BS16: 1096.8 | BT16: 1035.1 | BU16: 1032.2 | BV16: 1007.4 | BW16: 1115 | BX16: 1084.7 | BY16: 1156.5 | BZ16: 1108 | CA16: 1213 | CB16: 1166.1 | CC16: 1273.9 | CD16: 1120.2 | CE16: 1239.7 | CF16: 1189.5 | CG16: 1146.7 | CH16: 1123 | CI16: 1203.2 | CJ16: 1223 | CK16: 1366.5 | CL16: 1215 | CM16: 1262.9 | CN16: 1212.7 | CO16: 1335.8 | CP16: 1281.9 | CQ16: 1408.3 | CR16: 1182.3 | CS16: 749.6 | CT16: 562.7 | CU16: 379.5 | CV16: 374.5 | CW16: 384.8 | CX16: 284.8 | CY16: 283.2 | CZ16: 278.7 | DA16: 348.2 | DB16: 283.1 | DC16: 243.8 | DD16: 257.4 | DE16: 253.1 | DF16: 219.5 | DG16: 253.7 | DH16: 237.9 | DI16: 229.1 | DJ16: 212.8 | DK16: 210.7 | DL16: 148.9 | DM16: 153 | DN16: 147.5 | DO16: 140.8 | DP16: 140.6 | DQ16: 152.2 | DR16: 122.6 | DS16: 128 | DT16: 109.9 | DU16: 110.8 | DV16: 107.2 | DW16: 104.3 | DX16: 105.4 | DY16: 101.8 | DZ16: 98.4 | EA16: 96.6 | EB16: 112.7 | EC16: 98.9 | ED16: 95.8 | EE16: 95.4 | EF16: 101.7 | EG16: 137.4 | EH16: 93.1 | EI16: 87.3 | EJ16: 81.4 | EK16: 75.1 | EL16: 106.5 | EM16: 106.5 | EN16: 61.4 | EO16: 0 | EP16: 0 | EQ16: 0
A17: =+A23+1 -> 28 | B17: Sovaldi | C17: GILD | D17: HCV | G17: =SUM(AK17:GH17) -> 20663.11 | I17: =SUM(AK17:AN17) -> 8690.11 | J17: =SUM(AO17:AR17) -> 5461 | K17: =SUM(AS17:AV17) -> 5007 | L17: =SUM(AW17:AZ17) -> 1388 | M17: =SUM(BA17:BD17) -> 117 | N17: =SUM(BE17:BH17) -> 0 | O17: =SUM(BI17:BL17) -> 0 | P17: =SUM(BM17:BP17) -> 0 | Q17: =SUM(BQ17:BT17) -> 0 | R17: =SUM(BU17:BX17) -> 0 | S17: =SUM(BY17:CB17) -> 0 | T17: =SUM(CC17:CF17) -> 0 | U17: =SUM(CG17:CJ17) -> 0 | V17: =SUM(CK17:CN17) -> 0 | AK17: 139.435 | AL17: 2274.349 | AM17: 3480.326 | AN17: 2796 | AO17: 1732 | AP17: 972 | AQ17: 1291 | AR17: 1466 | AS17: 1547 | AT17: 1277 | AU17: 1358 | AV17: 825 | AW17: 541 | AX17: 313 | AY17: 315 | AZ17: 219 | BA17: 117
A18: =+A22+1 -> 25 | B18: Skyrizi | C18: ABBV | D18: Autoimmune | G18: =SUM(AK18:GH18) -> 22547 | I18: =SUM(AK18:AN18) -> 655 | J18: =SUM(AO18:AR18) -> 1864 | K18: =SUM(AS18:AV18) -> 3305 | L18: =SUM(AW18:AZ18) -> 5585 | M18: =SUM(BA18:BD18) -> 8411 | N18: =SUM(BE18:BH18) -> 2727 | O18: =SUM(BI18:BL18) -> 0 | P18: =SUM(BM18:BP18) -> 0 | Q18: =SUM(BQ18:BT18) -> 0 | R18: =SUM(BU18:BX18) -> 0 | S18: =SUM(BY18:CB18) -> 0 | T18: =SUM(CC18:CF18) -> 0 | U18: =SUM(CG18:CJ18) -> 0 | V18: =SUM(CK18:CN18) -> 0 | AK18: 48 | AL18: 91 | AM18: 216 | AN18: 300 | AO18: 330 | AP18: 435 | AQ18: 525 | AR18: 574 | AS18: 674 | AT18: 796 | AU18: 895 | AV18: 940 | AW18: 1252 | AX18: 1397 | AY18: 1576 | AZ18: 1360 | BA18: 1883 | BB18: 2126 | BC18: 2394 | BD18: 2008 | BE18: 2727
A19: =+A40+1 -> 34 | B19: Vyvgart | C19: ARGX | D19: Autoimmune | E19: 1 | G19: =SUM(AK19:GH19) -> 3777.482 | I19: =SUM(AK19:AN19) -> 400.721 | J19: =SUM(AO19:AR19) -> 1190.761 | K19: =SUM(AS19:AV19) -> 2186 | L19: =SUM(AW19:AZ19) -> 0 | M19: =SUM(BA19:BD19) -> 0 | AK19: 21.163 | AL19: 74.833 | AM19: 131.329 | AN19: 173.396 | AO19: 218 | AP19: 269.313 | AQ19: 329.097 | AR19: 374.351 | AS19: =876-477.635 -> 398.365 | AT19: =876-AS19 -> 477.635 | AU19: 573 | AV19: 737
A20: =+A31+1 -> 21 | B20: Cosentyx | C20: NVS | D20: Autoimmune | F20: Q115 | G20: =SUM(AK20:GH20) -> 31129 | I20: =SUM(AK20:AN20) -> 209 | J20: =SUM(AO20:AR20) -> 1128 | K20: =SUM(AS20:AV20) -> 2071 | L20: =SUM(AW20:AZ20) -> 2837 | M20: =SUM(BA20:BD20) -> 3551 | N20: =SUM(BE20:BH20) -> 3995 | O20: =SUM(BI20:BL20) -> 4718 | P20: =SUM(BM20:BP20) -> 4788 | Q20: =SUM(BQ20:BT20) -> 4980 | R20: =SUM(BU20:BX20) -> 2852 | S20: =SUM(BY20:CB20) -> 0 | T20: =SUM(CC20:CF20) -> 0 | U20: =SUM(CG20:CJ20) -> 0 | V20: =SUM(CK20:CN20) -> 0 | AK20: 22 | AL20: 30 | AM20: 88 | AN20: 121 | AO20: 176 | AP20: 260 | AQ20: 301 | AR20: 391 | AS20: 410 | AT20: 490 | AU20: 556 | AV20: 615 | AW20: 580 | AX20: 701 | AY20: 750 | AZ20: 806 | BA20: 791 | BB20: 858 | BC20: 937 | BD20: 965 | BE20: 930 | BF20: 944 | BG20: 1012 | BH20: 1109 | BI20: 1053 | BJ20: 1175 | BK20: 1247 | BL20: 1243 | BM20: 1159 | BN20: 1275 | BO20: 1274 | BP20: 1080 | BQ20: 1076 | BR20: 1272 | BS20: 1329 | BT20: 1303 | BU20: 1326 | BV20: 1526
A21: =+A36+1 -> 31 | B21: Rinvoq | C21: ABBV | D21: Autoimmune | G21: =SUM(AK21:GH21) -> 11443 | I21: =SUM(AK21:AN21) -> 282 | J21: =SUM(AO21:AR21) -> 1177 | K21: =SUM(AS21:AV21) -> 2027 | L21: =SUM(AW21:AZ21) -> 3069 | M21: =SUM(BA21:BD21) -> 4888 | N21: =SUM(BE21:BH21) -> 0 | O21: =SUM(BI21:BL21) -> 0 | P21: =SUM(BM21:BP21) -> 0 | Q21: =SUM(BQ21:BT21) -> 0 | R21: =SUM(BU21:BX21) -> 0 | S21: =SUM(BY21:CB21) -> 0 | T21: =SUM(CC21:CF21) -> 0 | U21: =SUM(CG21:CJ21) -> 0 | V21: =SUM(CK21:CN21) -> 0 | AK21: 14 | AL21: 33 | AM21: 86 | AN21: 149 | AO21: 215 | AP21: 281 | AQ21: 303 | AR21: 378 | AS21: 453 | AT21: 517 | AU21: 465 | AV21: 592 | AW21: 695 | AX21: 770 | AY21: 686 | AZ21: 918 | BA21: 1110 | BB21: 1255 | BC21: 1093 | BD21: 1430
A22: =+A9+1 -> 24 | B22: Zytiga | C22: JNJ | D22: Oncology | E22: 1 | G22: =SUM(AK22:GH22) -> 25264.5 | I22: =SUM(AK22:AN22) -> 297.5 | J22: =SUM(AO22:AR22) -> 961 | K22: =SUM(AS22:AV22) -> 1698 | L22: =SUM(AW22:AZ22) -> 2237 | M22: =SUM(BA22:BD22) -> 2231 | N22: =SUM(BE22:BH22) -> 2260 | O22: =SUM(BI22:BL22) -> 2505 | P22: =SUM(BM22:BP22) -> 3498 | Q22: =SUM(BQ22:BT22) -> 2795 | R22: =SUM(BU22:BX22) -> 2470 | S22: =SUM(BY22:CB22) -> 2297 | T22: =SUM(CC22:CF22) -> 1770 | U22: =SUM(CG22:CJ22) -> 245 | V22: =SUM(CK22:CN22) -> 0 | AK22: 5 | AL22: =AVERAGE(AK22,AM22) -> 50 | AM22: 95 | AN22: =AVERAGE(AM22,AO22) -> 147.5 | AO22: 200 | AP22: 232 | AQ22: 265 | AR22: 264 | AS22: 344 | AT22: 395 | AU22: 464 | AV22: 495 | AW22: 512 | AX22: 562 | AY22: 568 | AZ22: 595 | BA22: 556 | BB22: 546 | BC22: 548 | BD22: 581 | BE22: 558 | BF22: 601 | BG22: 582 | BH22: 519 | BI22: 523 | BJ22: 558 | BK22: 669 | BL22: 755 | BM22: 845 | BN22: 909 | BO22: 958 | BP22: 786 | BQ22: 679 | BR22: 698 | BS22: 741 | BT22: 677 | BU22: 690 | BV22: 568 | BW22: 590 | BX22: 622 | BY22: 638 | BZ22: 563 | CA22: 548 | CB22: 548 | CC22: 539 | CD22: 505 | CE22: 456 | CF22: 270 | CG22: 245
A23: =+A35+1 -> 27 | B23: Imbruvica | C23: JNJ | D23: Oncology | E23: 1 | G23: =SUM(AK23:GH23) -> 23168 | I23: =SUM(AK23:AN23) -> 200 | J23: =SUM(AO23:AR23) -> 689 | K23: =SUM(AS23:AV23) -> 1251 | L23: =SUM(AW23:AZ23) -> 1893 | M23: =SUM(BA23:BD23) -> 2615 | N23: =SUM(BE23:BH23) -> 3411 | O23: =SUM(BI23:BL23) -> 4128 | P23: =SUM(BM23:BP23) -> 4369 | Q23: =SUM(BQ23:BT23) -> 3785 | R23: =SUM(BU23:BX23) -> 827 | S23: =SUM(BY23:CB23) -> 0 | T23: =SUM(CC23:CF23) -> 0 | U23: =SUM(CG23:CJ23) -> 0 | V23: =SUM(CK23:CN23) -> 0 | AK23: 10 | AL23: 42 | AM23: 56 | AN23: 92 | AO23: 116 | AP23: 154 | AQ23: 184 | AR23: 235 | AS23: 261 | AT23: 295 | AU23: 349 | AV23: 346 | AW23: 409 | AX23: 450 | AY23: 512 | AZ23: 522 | BA23: 587 | BB23: 620 | BC23: 705 | BD23: 703 | BE23: 784 | BF23: 831 | BG23: 921 | BH23: 875 | BI23: 1031 | BJ23: 949 | BK23: 1031 | BL23: 1117 | BM23: 1125 | BN23: 1116 | BO23: 1066 | BP23: 1062 | BQ23: 1038 | BR23: 970 | BS23: 911 | BT23: 866 | BU23: 827
A24: =+A17+1 -> 29 | B24: Isentress | C24: MRK | D24: HIV | G24: =SUM(AK24:GH24) -> 16856 | I24: =SUM(AK24:AN24) -> 348 | J24: =SUM(AO24:AR24) -> 751 | K24: =SUM(AS24:AV24) -> 1090 | L24: =SUM(AW24:AZ24) -> 1359 | M24: =SUM(BA24:BD24) -> 1515 | N24: =SUM(BE24:BH24) -> 1643 | O24: =SUM(BI24:BL24) -> 1673 | P24: =SUM(BM24:BP24) -> 1511 | Q24: =SUM(BQ24:BT24) -> 1387 | R24: =SUM(BU24:BX24) -> 1205 | S24: =SUM(BY24:CB24) -> 1141 | T24: =SUM(CC24:CF24) -> 975 | U24: =SUM(CG24:CJ24) -> 857 | V24: =SUM(CK24:CN24) -> 768 | AK24: 47 | AL24: 77 | AM24: 107 | AN24: 117 | AO24: 148 | AP24: 172 | AQ24: 197 | AR24: 234 | AS24: 232 | AT24: 267 | AU24: 278 | AV24: 313 | AW24: 292 | AX24: 337 | AY24: 343 | AZ24: 387 | BA24: 337 | BB24: 398 | BC24: 399 | BD24: 381 | BE24: 362 | BF24: 412 | BG24: 427 | BH24: 442 | BI24: 390 | BJ24: 453 | BK24: 412 | BL24: 418 | BM24: 385 | BN24: 375 | BO24: 377 | BP24: 374 | BQ24: 340 | BR24: 338 | BS24: 372 | BT24: 337 | BU24: 305 | BV24: 282 | BW24: 310 | BX24: 308 | BY24: 281 | BZ24: 305 | CA24: 275 | CB24: 280 | CC24: 255 | CD24: 247 | CE24: 250 | CF24: 223 | CG24: 245 | CH24: 196 | CI24: 205 | CJ24: 211 | CK24: 209 | CL24: 192 | CM24: 189 | CN24: 178 | CO24: 158 | CP24: 147 | CQ24: 161 | CR24: 167
A25: =+A6+1 -> 11 | B25: Humalog | C25: LLY | D25: Diabetes | G25: =SUM(AK25:GH25) -> 48471.867 | I25: =SUM(AK25:AN25) -> 11 | J25: =SUM(AO25:AR25) -> 80 | K25: =SUM(AS25:AV25) -> 167.5 | L25: =SUM(AW25:AZ25) -> 280.4 | M25: =SUM(BA25:BD25) -> 472.2 | N25: =SUM(BE25:BH25) -> 739.2 | O25: =SUM(BI25:BL25) -> 954.9 | P25: =SUM(BM25:BP25) -> 1069.6 | Q25: =SUM(BQ25:BT25) -> 1131.6 | R25: =SUM(BU25:BX25) -> 1241.7667 | S25: =SUM(BY25:CB25) -> 1372.1 | T25: =SUM(CC25:CF25) -> 1622 | U25: =SUM(CG25:CJ25) -> 1818.6 | V25: =SUM(CK25:CN25) -> 2042 | W25: =SUM(CO25:CR25) -> 2155.4 | X25: =SUM(CS25:CV25) -> 2458.9 | Y25: =SUM(CW25:CZ25) -> 2453.1 | Z25: =SUM(DA25:DD25) -> 2700 | AA25: =SUM(DE25:DH25) -> 2773.5 | AK25: 1 | AL25: 2 | AM25: 3 | AN25: 5 | AO25: 10 | AP25: 15 | AQ25: 25 | AR25: 30 | AS25: 32 | AT25: 42.6 | AU25: 42.5 | AV25: 50.4 | AW25: 58.7 | AX25: 72.9 | AY25: 72.1 | AZ25: 76.7 | BA25: 90.6 | BB25: 110.8 | BC25: 125.2 | BD25: 145.6 | BE25: 164.3 | BF25: 192.7 | BG25: 177.4 | BH25: 204.8 | BI25: 214.1 | BJ25: 237.9 | BK25: 248.8 | BL25: 254.1 | BM25: 240.2 | BN25: 276.9 | BO25: 267.2 | BP25: 285.3 | BQ25: 264.6 | BR25: 284.6 | BS25: 286.2 | BT25: 296.2 | BU25: 306.66667 | BV25: 309.1 | BW25: 305 | BX25: 321 | BY25: 322 | BZ25: 352.2 | CA25: 339.5 | CB25: 358.4 | CC25: 362.5 | CD25: 414.2 | CE25: 407.4 | CF25: 437.9 | CG25: 432.6 | CH25: 457.9 | CI25: 450.6 | CJ25: 477.5 | CK25: 500.2 | CL25: 530.8 | CM25: 506.4 | CN25: 504.6 | CO25: 494 | CP25: 549.1 | CQ25: 525.4 | CR25: 586.9 | CS25: 593.2 | CT25: 662 | CU25: 590.3 | CV25: 613.4 | CW25: 575.8 | CX25: 616 | CY25: 632.7 | CZ25: 628.6 | DA25: 616 | DB25: 733.9 | DC25: 650 | DD25: 700.1 | DE25: 706.1 | DF25: 729.1 | DG25: 684 | DH25: 654.3 | DI25: 705 | DJ25: 798.7 | DK25: 606.3 | DL25: 701.9 | DM25: 640.8 | DN25: 819.8 | DO25: 708.4 | DP25: 678.4 | DQ25: 696.2 | DR25: 782.2 | DS25: 791.7 | DT25: 769.8 | DU25: 664.6 | DV25: 770.4 | DW25: 730.8 | DX25: 677.6 | DY25: 648.9 | DZ25: 763.4 | EA25: 695.8 | EB25: 555.1 | EC25: 656.9 | ED25: 718.1 | EE25: 617.1 | EF25: 607.6 | EG25: 626.7 | EH25: 601.7 | EI25: 618.2 | EJ25: 447.1 | EK25: 447 | EL25: 548.3 | EM25: 460.9 | EN25: 440.4 | EO25: 395.4 | EP25: 366.6 | EQ25: 538.7 | ER25: 631.6
A26: =+A25+1 -> 12 | B26: Darzalex | C26: JNJ | D26: Oncology | E26: 1 | G26: =SUM(AK26:GH26) -> 43368 | I26: =SUM(AK26:AN26) -> 383 | J26: =SUM(AO26:AR26) -> 1071 | K26: =SUM(AS26:AV26) -> 1812 | L26: =SUM(AW26:AZ26) -> 2752 | M26: =SUM(BA26:BD26) -> 3767 | N26: =SUM(BE26:BH26) -> 5631 | O26: =SUM(BI26:BL26) -> 7539 | P26: =SUM(BM26:BP26) -> 9277 | Q26: =SUM(BQ26:BT26) -> 11136 | R26: =SUM(BU26:BX26) -> 0 | S26: =SUM(BY26:CB26) -> 0 | T26: =SUM(CC26:CF26) -> 0 | U26: =SUM(CG26:CJ26) -> 0 | V26: =SUM(CK26:CN26) -> 0 | AK26: 20 | AL26: 101 | AM26: 108 | AN26: =AVERAGE(AM26,AO26) -> 154 | AO26: 200 | AP26: 255 | AQ26: 299 | AR26: 317 | AS26: 371 | AT26: 432 | AU26: 511 | AV26: 498 | AW26: 584 | AX26: 629 | AY26: 774 | AZ26: 765 | BA26: 830 | BB26: 937 | BC26: 901 | BD26: 1099 | BE26: 1253 | BF26: 1365 | BG26: 1433 | BH26: 1580 | BI26: 1645 | BJ26: 1856 | BK26: 1986 | BL26: 2052 | BM26: 2083 | BN26: 2264 | BO26: 2431 | BP26: 2499 | BQ26: 2550 | BR26: 2692 | BS26: 2878 | BT26: 3016
A27: =+A26+1 -> 13 | B27: Gardasil | C27: MRK | D27: Vaccine, Oncology | E27: 1 | G27: =SUM(AK27:GH27) -> 41658 | I27: =SUM(AK27:AN27) -> 600 | J27: =SUM(AO27:AR27) -> 1616 | K27: =SUM(AS27:AV27) -> 1400 | L27: =SUM(AW27:AZ27) -> 1089 | M27: =SUM(BA27:BD27) -> 970 | N27: =SUM(BE27:BH27) -> 1280 | O27: =SUM(BI27:BL27) -> 1737 | P27: =SUM(BM27:BP27) -> 1825 | Q27: =SUM(BQ27:BT27) -> 1714 | R27: =SUM(BU27:BX27) -> 1927 | S27: =SUM(BY27:CB27) -> 2327 | T27: =SUM(CC27:CF27) -> 2437 | U27: =SUM(CG27:CJ27) -> 3329 | V27: =SUM(CK27:CN27) -> 3996 | AK27: 10 | AL27: 70 | AM27: 155 | AN27: 365 | AO27: 358 | AP27: 418 | AQ27: 450 | AR27: 390 | AS27: 326 | AT27: 401 | AU27: 411 | AV27: 262 | AW27: 268 | AX27: 311 | AY27: 277 | AZ27: 233 | BA27: 219 | BB27: 316 | BC27: 221 | BD27: 214 | BE27: 277 | BF27: 445 | BG27: 274 | BH27: 284 | BI27: 324 | BJ27: 581 | BK27: 442 | BL27: 390 | BM27: 383 | BN27: 665 | BO27: 394 | BP27: 383 | BQ27: 409 | BR27: 590 | BS27: 356 | BT27: 359 | BU27: 427 | BV27: 625 | BW27: 497 | BX27: 378 | BY27: 393 | BZ27: 860 | CA27: 542 | CB27: 532 | CC27: 469 | CD27: 675 | CE27: 633 | CF27: 660 | CG27: 608 | CH27: 1048 | CI27: 835 | CJ27: 838 | CK27: 886 | CL27: 1320 | CM27: 693 | CN27: 1097 | CO27: 656 | CP27: 1187 | CQ27: 998 | CR27: 917 | CS27: 1234 | CT27: 1993 | CU27: 1528 | CV27: 1460 | CW27: 1674 | CX27: 2294 | CY27: 1470
A28: =+A13+1 -> 15 | B28: Viagra | C28: PFE | D28: Cardiovascular | E28: 1 | G28: =SUM(AK28:GH28) -> 34660 | I28: =SUM(AK28:AN28) -> 963 | J28: =SUM(AO28:AR28) -> 1155 | K28: =SUM(AS28:AV28) -> 1393 | L28: =SUM(AW28:AZ28) -> 1563 | M28: =SUM(BA28:BD28) -> 1788 | N28: =SUM(BE28:BH28) -> 1820 | O28: =SUM(BI28:BL28) -> 1699 | P28: =SUM(BM28:BP28) -> 1597 | Q28: =SUM(BQ28:BT28) -> 1701 | R28: =SUM(BU28:BX28) -> 1790 | S28: =SUM(BY28:CB28) -> 1928 | T28: =SUM(CC28:CF28) -> 1917 | U28: =SUM(CG28:CJ28) -> 1919 | V28: =SUM(CK28:CN28) -> 2007 | W28: =SUM(CO28:CR28) -> 2016 | X28: =SUM(CS28:CV28) -> 2130 | AK28: 402 | AL28: 138 | AM28: 233 | AN28: 190 | AO28: 305 | AP28: 245 | AQ28: 277 | AR28: 328 | AS28: 304 | AT28: 332 | AU28: 380 | AV28: 377 | AW28: 351 | AX28: 375 | AY28: 415 | AZ28: 422 | BA28: 385 | BB28: 437 | BC28: 491 | BD28: 475 | BE28: 419 | BF28: 476 | BG28: 509 | BH28: 416 | BI28: 389 | BJ28: 403 | BK28: 469 | BL28: 438 | BM28: 391 | BN28: 386 | BO28: 430 | BP28: 390 | BQ28: 394 | BR28: 423 | BS28: 450 | BT28: 434 | BU28: 382 | BV28: 450 | BW28: 498 | BX28: 460 | BY28: 463 | BZ28: 509 | CA28: 502 | CB28: 454 | CC28: 423 | CD28: 466 | CE28: 549 | CF28: 479 | CG28: 491 | CH28: 459 | CI28: 499 | CJ28: 470 | CK28: 495 | CL28: 493 | CM28: 523 | CN28: 496 | CO28: 485 | CP28: 517 | CQ28: 553 | CR28: 461 | CS28: 484 | CT28: 460 | CU28: 812 | CV28: 374 | CW28: 427 | CX28: 427 | CY28: 464 | CZ28: 396 | DA28: 448 | DB28: 430 | DC28: 434 | DD28: 396 | DE28: 401 | DF28: 386 | DG28: 381 | DH28: 338 | DI28: 348 | DJ28: 308 | DK28: 265 | DL28: 249 | DM28: 193 | DN28: 137 | DO28: 127 | DP28: 145 | DQ28: 114 | DR28: 120 | DS28: 119 | DT28: 127 | DU28: 94
A29: =+A28+1 -> 16 | B29: Alimta | C29: LLY | D29: Oncology | G29: =SUM(AK29:GH29) -> 34155.5 | I29: =SUM(AK29:AN29) -> 142.5 | J29: =SUM(AO29:AR29) -> 463.2 | K29: =SUM(AS29:AV29) -> 611.4 | L29: =SUM(AW29:AZ29) -> 854 | M29: =SUM(BA29:BD29) -> 1154.8 | N29: =SUM(BE29:BH29) -> 1706.1 | O29: =SUM(BI29:BL29) -> 2208.5 | P29: =SUM(BM29:BP29) -> 2461.1 | Q29: =SUM(BQ29:BT29) -> 2594.2 | R29: =SUM(BU29:BX29) -> 2702.9 | S29: =SUM(BY29:CB29) -> 2792 | T29: =SUM(CC29:CF29) -> 2493 | U29: =SUM(CG29:CJ29) -> 2283.3 | V29: =SUM(CK29:CN29) -> 2062.5 | AK29: 11.6 | AL29: 17.8 | AM29: 40 | AN29: 73.1 | AO29: 93.9 | AP29: 111.2 | AQ29: 122.3 | AR29: 135.8 | AS29: 130 | AT29: 153 | AU29: 157 | AV29: 171.4 | AW29: 187.8 | AX29: 207.1 | AY29: 215 | AZ29: 244.1 | BA29: 247.2 | BB29: 275 | BC29: 313.9 | BD29: 318.7 | BE29: 335.3 | BF29: 385.3 | BG29: 461.9 | BH29: 523.6 | BI29: 527.4 | BJ29: 551.8 | BK29: 560.3 | BL29: 569 | BM29: 579.9 | BN29: 613.4 | BO29: 629.7 | BP29: 638.1 | BQ29: 606.8 | BR29: 659.5 | BS29: 643.6 | BT29: 684.3 | BU29: 616.8 | BV29: 669.4 | BW29: 690.5 | BX29: 726.2 | BY29: 632 | BZ29: 711.6 | CA29: 723.4 | CB29: 725 | CC29: 573 | CD29: 664.3 | CE29: 628.5 | CF29: 627.2 | CG29: 564.2 | CH29: 607.1 | CI29: 570.4 | CJ29: 541.6 | CK29: 489.9 | CL29: 532.9 | CM29: 514.5 | CN29: 525.2 | CO29: 499.6 | CP29: 555.9 | CQ29: 520.5 | CR29: 556.9 | CS29: 499.2 | CT29: 577.8 | CU29: 508.2 | CV29: 530.7 | CW29: 560.1 | CX29: 539.1 | CY29: 578 | CZ29: 652.7 | DA29: 559 | DB29: 610.6 | DC29: 457 | DD29: 434.9 | DE29: 343.9 | DF29: 227.7 | DG29: 119.4 | DH29: 236.6 | DI29: 58.2
A30: =+A29+1 -> 17 | B30: Cymbalta | C30: LLY | D30: Psychiatry | E30: 2 | G30: =SUM(AK30:GH30) -> 32887.4 | I30: =SUM(AK30:AN30) -> 362 | J30: =SUM(AO30:AR30) -> 954.6 | K30: =SUM(AS30:AV30) -> 1734.4 | L30: =SUM(AW30:AZ30) -> 2401 | M30: =SUM(BA30:BD30) -> 2891.3 | N30: =SUM(BE30:BH30) -> 3291.9 | O30: =SUM(BI30:BL30) -> 3722.1 | P30: =SUM(BM30:BP30) -> 4587.3 | Q30: =SUM(BQ30:BT30) -> 5481.6 | R30: =SUM(BU30:BX30) -> 3138.5 | S30: =SUM(BY30:CB30) -> 1296.4 | T30: =SUM(CC30:CF30) -> 901.7 | U30: =SUM(CG30:CJ30) -> 876.5 | V30: =SUM(CK30:CN30) -> 727.5 | AK30: 32.5 | AL30: 61.3 | AM30: 106.8 | AN30: 161.4 | AO30: 182.8 | AP30: 228.8 | AQ30: 233 | AR30: 310 | AS30: 349 | AT30: 424.1 | AU30: 441.8 | AV30: 519.5 | AW30: 513.2 | AX30: 628.3 | AY30: 605.1 | AZ30: 654.4 | BA30: 716.4 | BB30: 721.2 | BC30: 709.3 | BD30: 744.4 | BE30: 790.2 | BF30: 830.8 | BG30: 803.2 | BH30: 867.7 | BI30: 825.3 | BJ30: 984.6 | BK30: 908.8 | BL30: 1003.4 | BM30: 1068.6 | BN30: 1180.7 | BO30: 1114.9 | BP30: 1223.1 | BQ30: 1235.8 | BR30: 1420.4 | BS30: 1328.2 | BT30: 1497.2 | BU30: 1375.8 | BV30: 883.2 | BW30: 478.2 | BX30: 401.3 | BY30: 368 | BZ30: 367.3 | CA30: 287 | CB30: 274.1 | CC30: 242.9 | CD30: 223.6 | CE30: 198.7 | CF30: 236.5 | CG30: 313.5 | CH30: 181.8 | CI30: 174.6 | CJ30: 206.6 | CK30: 183.2 | CL30: 192.8 | CM30: 169.6 | CN30: 181.9 | CO30: 172 | CP30: 184.5 | CQ30: 164.1
A31: =+A7+1 -> 20 | B31: Trulicity | C31: LLY | D31: Diabetes | G31: =SUM(AK31:GH31) -> 31498 | I31: =SUM(AK31:AN31) -> 146.5 | J31: =SUM(AO31:AR31) -> 701 | K31: =SUM(AS31:AV31) -> 1717.8 | L31: =SUM(AW31:AZ31) -> 2923.3 | M31: =SUM(BA31:BD31) -> 3844.4 | N31: =SUM(BE31:BH31) -> 4773.9 | O31: =SUM(BI31:BL31) -> 6090.5 | P31: =SUM(BM31:BP31) -> 7387.3 | Q31: =SUM(BQ31:BT31) -> 3913.3 | R31: =SUM(BU31:BX31) -> 0 | S31: =SUM(BY31:CB31) -> 0 | T31: =SUM(CC31:CF31) -> 0 | U31: =SUM(CG31:CJ31) -> 0 | V31: =SUM(CK31:CN31) -> 0 | AK31: 10.2 | AL31: 18.3 | AM31: 44.3 | AN31: 73.7 | AO31: 112.5 | AP31: 143.6 | AQ31: 201.3 | AR31: 243.6 | AS31: 337 | AT31: 372.9 | AU31: 480.2 | AV31: 527.7 | AW31: 649 | AX31: 678.3 | AY31: 779.8 | AZ31: 816.2 | BA31: 924.7 | BB31: 879.7 | BC31: 1028.5 | BD31: 1011.5 | BE31: 1208.1 | BF31: 1229.4 | BG31: 1229.8 | BH31: 1106.6 | BI31: 1502.4 | BJ31: 1452.4 | BK31: 1535.6 | BL31: 1600.1 | BM31: 1883.7 | BN31: 1741.3 | BO31: 1911.9 | BP31: 1850.4 | BQ31: 1936.2 | BR31: 1977.1
A32: =+A5+1 -> 6 | B32: Prevnar | C32: PFE | D32: Vaccine | G32: =SUM(I32:BN32) -> 82695.365 | I32: 460.6 | J32: 798.2 | K32: 647.5 | L32: 945.6 | M32: 1053.6 | N32: 1508.3 | O32: 1961.3 | P32: 2,439 | Q32: 2,716 | R32: 1825.265 | S32: 3669 | T32: 4145 | U32: 4117 | V32: 3974 | W32: 4464 | X32: 6247 | Y32: 5719 | Z32: 5601 | AA32: 5802 | AB32: 5847 | AC32: 5850 | AD32: 5274 | AE32: 6337 | AF32: 6449
A33: =+A20+1 -> 22 | B33: Cialis | C33: LLY | D33: Cardiovascular | E33: 2 | G33: =SUM(AK33:GH33) -> 28918.5 | I33: =SUM(AK33:AN33) -> 203.3 | J33: =SUM(AO33:AR33) -> 540.1 | K33: =SUM(AS33:AV33) -> 690.4 | L33: =SUM(AW33:AZ33) -> 943.3 | M33: =SUM(BA33:BD33) -> 1216.3 | N33: =SUM(BE33:BH33) -> 1444.5 | O33: =SUM(BI33:BL33) -> 1559.1 | P33: =SUM(BM33:BP33) -> 1699.4 | Q33: =SUM(BQ33:BT33) -> 1875.6 | R33: =SUM(BU33:BX33) -> 1926.8 | S33: =SUM(BY33:CB33) -> 2159.4 | T33: =SUM(CC33:CF33) -> 2291 | U33: =SUM(CG33:CJ33) -> 2310.7 | V33: =SUM(CK33:CN33) -> 2471.7 | AK33: 21.5 | AL33: 37.5 | AM33: 50.2 | AN33: 94.1 | AO33: 108.3 | AP33: 125 | AQ33: 154.1 | AR33: 152.7 | AS33: 150.1 | AT33: 165.1 | AU33: 180.1 | AV33: 195.1 | AW33: 210.1 | AX33: 225.1 | AY33: 240.1 | AZ33: 268 | BA33: 266 | BB33: 293.1 | BC33: 311 | BD33: 346.2 | BE33: 336.9 | BF33: 362.2 | BG33: 376.6 | BH33: 368.8 | BI33: 358.8 | BJ33: 363.6 | BK33: 397.2 | BL33: 439.5 | BM33: 408.3 | BN33: 418.7 | BO33: 406.5 | BP33: 465.9 | BQ33: 434.4 | BR33: 477.2 | BS33: 469.8 | BT33: 494.2 | BU33: 461.8 | BV33: 469.5 | BW33: 482.1 | BX33: 513.4 | BY33: 515 | BZ33: 529.4 | CA33: 526.7 | CB33: 588.3 | CC33: 532.4 | CD33: 567.8 | CE33: 568.4 | CF33: 622.4 | CG33: 538.3 | CH33: 567.9 | CI33: 566.1 | CJ33: 638.4 | CK33: 576.7 | CL33: 630.5 | CM33: 588.2 | CN33: 676.3 | CO33: 533.6 | CP33: 627.3 | CQ33: 564.9 | CR33: 597.4 | CS33: 495.4 | CT33: 538.7 | CU33: 467.1 | CV33: 350.7 | CW33: 308.2 | CX33: 200.2 | CY33: 184.3 | CZ33: 197.8 | DA33: 193 | DB33: 130.7 | DC33: 162.5 | DD33: 120.9 | DE33: 126.8 | DF33: 281 | DG33: 130.9 | DH33: 179.7 | DI33: 217.7 | DJ33: 147 | DK33: 115.7 | DL33: 106.9 | DM33: 100.3 | DN33: 115.6 | DO33: 86.8 | DP33: 78.8 | DQ33: 139.3 | DR33: 87.7
A34: =+A22+1 -> 25 | B34: Entresto | C34: NVS | D34: Cardiovascular | E34: 1 | G34: =SUM(AK34:GH34) -> 23953 | I34: =SUM(AK34:AN34) -> 70 | J34: =SUM(AO34:AR34) -> 315 | K34: =SUM(AS34:AV34) -> 752 | L34: =SUM(AW34:AZ34) -> 1367 | M34: =SUM(BA34:BD34) -> 2097 | N34: =SUM(BE34:BH34) -> 3023 | O34: =SUM(BI34:BL34) -> 4091 | P34: =SUM(BM34:BP34) -> 5341 | Q34: =SUM(BQ34:BT34) -> 6897 | R34: =SUM(BU34:BX34) -> 0 | S34: =SUM(BY34:CB34) -> 0 | T34: =SUM(CC34:CF34) -> 0 | U34: =SUM(CG34:CJ34) -> 0 | V34: =SUM(CK34:CN34) -> 0 | AK34: 16 | AL34: 5 | AM34: 17 | AN34: 32 | AO34: 53 | AP34: 68 | AQ34: 84 | AR34: 110 | AS34: 128 | AT34: 185 | AU34: 200 | AV34: 239 | AW34: 271 | AX34: 318 | AY34: 357 | AZ34: 421 | BA34: 430 | BB34: 518 | BC34: 569 | BD34: 580 | BE34: 632 | BF34: 716 | BG34: 789 | BH34: 886 | BI34: 924 | BJ34: 949 | BK34: 1093 | BL34: 1125 | BM34: 1135 | BN34: 1291 | BO34: 1399 | BP34: 1516 | BQ34: 1485 | BR34: 1635 | BS34: 1879 | BT34: 1898
A35: =+A34+1 -> 26 | B35: Paxlovid | C35: PFE | D35: COVID-19 | E35: 1 | G35: =SUM(AK35:GH35) -> 22574 | I35: =SUM(AK35:AN35) -> 17175 | J35: =SUM(AO35:AR35) -> 6248 | K35: =SUM(AS35:AV35) -> -849 | L35: =SUM(AW35:AZ35) -> 0 | M35: =SUM(BA35:BD35) -> 0 | N35: =SUM(BE35:BH35) -> 0 | O35: =SUM(BI35:BL35) -> 0 | P35: =SUM(BM35:BP35) -> 0 | Q35: =SUM(BQ35:BT35) -> 0 | R35: =SUM(BU35:BX35) -> 0 | S35: =SUM(BY35:CB35) -> 0 | T35: =SUM(CC35:CF35) -> 0 | U35: =SUM(CG35:CJ35) -> 0 | V35: =SUM(CK35:CN35) -> 0 | AK35: 76 | AL35: 1470 | AM35: 8115 | AN35: 7514 | AO35: 1834 | AP35: 4069 | AQ35: 143 | AR35: 202 | AS35: -3135 | AT35: 2035 | AU35: 251
A36: =+A24+1 -> 30 | B36: Xeljanz | C36: PFE | D36: Autoimmune | G36: =SUM(AK36:GH36) -> 16115 | I36: =SUM(AK36:AN36) -> 63 | J36: =SUM(AO36:AR36) -> 251 | K36: =SUM(AS36:AV36) -> 455 | L36: =SUM(AW36:AZ36) -> 821 | M36: =SUM(BA36:BD36) -> 1212 | N36: =SUM(BE36:BH36) -> 1631 | O36: =SUM(BI36:BL36) -> 2188 | P36: =SUM(BM36:BP36) -> 2347 | Q36: =SUM(BQ36:BT36) -> 2430 | R36: =SUM(BU36:BX36) -> 2025 | S36: =SUM(BY36:CB36) -> 1702 | T36: =SUM(CC36:CF36) -> 990 | U36: =SUM(CG36:CJ36) -> 0 | V36: =SUM(CK36:CN36) -> 0 | AK36: 6 | AL36: 0 | AM36: 22 | AN36: 35 | AO36: 46 | AP36: 52 | AQ36: 68 | AR36: 85 | AS36: 104 | AT36: 96 | AU36: 128 | AV36: 127 | AW36: 172 | AX36: 197 | AY36: 217 | AZ36: 235 | BA36: 278 | BB36: 250 | BC36: 336 | BD36: 348 | BE36: 410 | BF36: 326 | BG36: 463 | BH36: 432 | BI36: 553 | BJ36: 423 | BK36: 613 | BL36: 599 | BM36: 607 | BN36: 451 | BO36: 635 | BP36: 654 | BQ36: 696 | BR36: 538 | BS36: 586 | BT36: 610 | BU36: 721 | BV36: 372 | BW36: 430 | BX36: 502 | BY36: 493 | BZ36: 237 | CA36: 469 | CB36: 503 | CC36: 493 | CD36: 194 | CE36: 303
A37: =+A24+1 -> 30 | B37: Descovy | C37: GILD | D37: HIV | G37: =SUM(AK37:GH37) -> 12925 | I37: =SUM(AK37:AN37) -> 549 | J37: =SUM(AO37:AR37) -> 1328 | K37: =SUM(AS37:AV37) -> 1562 | L37: =SUM(AW37:AZ37) -> 1616 | M37: =SUM(BA37:BD37) -> 1762 | N37: =SUM(BE37:BH37) -> 1715 | O37: =SUM(BI37:BL37) -> 1946 | P37: =SUM(BM37:BP37) -> 1962 | Q37: =SUM(BQ37:BT37) -> 485 | R37: =SUM(BU37:BX37) -> 0 | S37: =SUM(BY37:CB37) -> 0 | T37: =SUM(CC37:CF37) -> 0 | U37: =SUM(CG37:CJ37) -> 0 | V37: =SUM(CK37:CN37) -> 0 | AK37: 61 | AL37: 88 | AM37: 149 | AN37: 251 | AO37: 286 | AP37: 316 | AQ37: 365 | AR37: 361 | AS37: 403 | AT37: 406 | AU37: 411 | AV37: 342 | AW37: 358 | AX37: 363 | AY37: 437 | AZ37: 458 | BA37: 417 | BB37: 508 | BC37: 478 | BD37: 359 | BE37: 435 | BF37: 433 | BG37: 473 | BH37: 374 | BI37: 460 | BJ37: 500 | BK37: 537 | BL37: 449 | BM37: 516 | BN37: 511 | BO37: 509 | BP37: 426 | BQ37: 485
A38: =+A37+1 -> 31 | B38: Vyndaqel | C38: PFE | D38: Rare | E38: 1 | G38: =SUM(AK38:GH38) -> 12080 | I38: =SUM(AK38:AN38) -> 180 | J38: =SUM(AO38:AR38) -> 877 | K38: =SUM(AS38:AV38) -> 1734 | L38: =SUM(AW38:AZ38) -> 2226 | M38: =SUM(BA38:BD38) -> 2750 | N38: =SUM(BE38:BH38) -> 4313 | O38: =SUM(BI38:BL38) -> 0 | P38: =SUM(BM38:BP38) -> 0 | Q38: =SUM(BQ38:BT38) -> 0 | R38: =SUM(BU38:BX38) -> 0 | S38: =SUM(BY38:CB38) -> 0 | T38: =SUM(CC38:CF38) -> 0 | AK38: 37 | AL38: 39 | AM38: 41 | AN38: 63 | AO38: 156 | AP38: 213 | AQ38: 231 | AR38: 277 | AS38: 351 | AT38: 429 | AU38: 453 | AV38: 501 | AW38: 501 | AX38: 561 | AY38: 612 | AZ38: 552 | BA38: 602 | BB38: 680 | BC38: 686 | BD38: 782 | BE38: 892 | BF38: 961 | BG38: 1137 | BH38: 1323
A39: =+A38+1 -> 32 | B39: Taltz | C39: LLY | D39: Autoimmune | G39: =SUM(AK39:GH39) -> 9986.4 | I39: =SUM(AK39:AN39) -> 209.7 | J39: =SUM(AO39:AR39) -> 609 | K39: =SUM(AS39:AV39) -> 1043.5 | L39: =SUM(AW39:AZ39) -> 1557.4 | M39: =SUM(BA39:BD39) -> 1748.2 | N39: =SUM(BE39:BH39) -> 2297.7 | O39: =SUM(BI39:BL39) -> 2520.9 | P39: =SUM(BM39:BP39) -> 0 | Q39: =SUM(BQ39:BT39) -> 0 | R39: =SUM(BU39:BX39) -> 0 | S39: =SUM(BY39:CB39) -> 0 | T39: =SUM(CC39:CF39) -> 0 | AK39: 19.3 | AL39: 32.5 | AM39: 61.3 | AN39: 96.6 | AO39: 138.7 | AP39: 151.3 | AQ39: 172.5 | AR39: 146.5 | AS39: 220.1 | AT39: 263.9 | AU39: 307 | AV39: 252.5 | AW39: 353.8 | AX39: 340 | AY39: 420.1 | AZ39: 443.5 | BA39: 395.2 | BB39: 454.5 | BC39: 495.3 | BD39: 403.2 | BE39: 569.1 | BF39: 593.1 | BG39: 647.4 | BH39: 488.1 | BI39: 606.2 | BJ39: 679.9 | BK39: 707.8 | BL39: 527
A40: =+A39+1 -> 33 | B40: Bridion | C40: MRK/SGP | G40: =SUM(AK40:GH40) -> 9091 | I40: =SUM(AK40:AN40) -> 200 | J40: =SUM(AO40:AR40) -> 261 | K40: =SUM(AS40:AV40) -> 289 | L40: =SUM(AW40:AZ40) -> 340 | M40: =SUM(BA40:BD40) -> 353 | N40: =SUM(BE40:BH40) -> 481 | O40: =SUM(BI40:BL40) -> 705 | P40: =SUM(BM40:BP40) -> 917 | Q40: =SUM(BQ40:BT40) -> 1130 | R40: =SUM(BU40:BX40) -> 1198 | S40: =SUM(BY40:CB40) -> 1532 | T40: =SUM(CC40:CF40) -> 1685 | AK40: 41 | AL40: 47 | AM40: 52 | AN40: 60 | AO40: 58 | AP40: 60 | AQ40: 68 | AR40: 75 | AS40: 63 | AT40: 69 | AU40: 75 | AV40: 82 | AW40: 73 | AX40: 82 | AY40: 90 | AZ40: 95 | BA40: 85 | BB40: 87 | BC40: 89 | BD40: 92 | BE40: 90 | BF40: 113 | BG40: 139 | BH40: 139 | BI40: 148 | BJ40: 163 | BK40: 185 | BL40: 209 | BM40: 204 | BN40: 240 | BO40: 217 | BP40: 256 | BQ40: 255 | BR40: 278 | BS40: 284 | BT40: 313 | BU40: 299 | BV40: 224 | BW40: 320 | BX40: 355 | BY40: 340 | BZ40: 387 | CA40: 369 | CB40: 436 | CC40: 395 | CD40: 426 | CE40: 423 | CF40: 441
A41: =+A19+1 -> 35 | B41: Tremfya | C41: JNJ | G41: =SUM(AK41:GH41) -> 8385 | I41: =SUM(AK41:AN41) -> 416 | J41: =SUM(AO41:AR41) -> 917 | K41: =SUM(AS41:AV41) -> 1235 | L41: =SUM(AW41:AZ41) -> 1816 | M41: =SUM(BA41:BD41) -> 2609 | N41: =SUM(BE41:BH41) -> 1392 | O41: =SUM(BI41:BL41) -> 0 | P41: =SUM(BM41:BP41) -> 0 | Q41: =SUM(BQ41:BT41) -> 0 | R41: =SUM(BU41:BX41) -> 0 | S41: =SUM(BY41:CB41) -> 0 | T41: =SUM(CC41:CF41) -> 0 | AK41: 47 | AL41: 72 | AM41: 126 | AN41: 171 | AO41: 175 | AP41: 217 | AQ41: 235 | AR41: 290 | AS41: 270 | AT41: 296 | AU41: 342 | AV41: 327 | AW41: 382 | AX41: 418 | AY41: 479 | AZ41: 537 | BA41: 693 | BB41: 590 | BC41: 597 | BD41: 729 | BE41: 752 | BF41: 640
A42: =+A41+1 -> 36 | B42: Jardiance | C42: LLY | G42: =SUM(AK42:GH42) -> 7600.6 | I42: =SUM(AK42:AN42) -> 60.4 | J42: =SUM(AO42:AR42) -> 201.9 | K42: =SUM(AS42:AV42) -> 447.6 | L42: =SUM(AW42:AZ42) -> 658.3 | M42: =SUM(BA42:BD42) -> 944.2 | N42: =SUM(BE42:BH42) -> 1153.9 | O42: =SUM(BI42:BL42) -> 1490.8 | P42: =SUM(BM42:BP42) -> 2066 | Q42: =SUM(BQ42:BT42) -> 577.5 | R42: =SUM(BU42:BX42) -> 0 | S42: =SUM(BY42:CB42) -> 0 | T42: =SUM(CC42:CF42) -> 0 | AK42: 19.3 | AL42: 11.1 | AM42: 15.4 | AN42: 14.6 | AO42: 38.2 | AP42: 40.1 | AQ42: 47.5 | AR42: 76.1 | AS42: 74 | AT42: 103.2 | AU42: 127.2 | AV42: 143.2 | AW42: 151 | AX42: 147.2 | AY42: 166.9 | AZ42: 193.2 | BA42: 203.6 | BB42: 231.9 | BC42: 240.7 | BD42: 268 | BE42: 267.5 | BF42: 262 | BG42: 310.8 | BH42: 313.6 | BI42: 312 | BJ42: 356.5 | BK42: 390.4 | BL42: 431.9 | BM42: 419.4 | BN42: 461 | BO42: 573.3 | BP42: 612.3 | BQ42: 577.5
A43: =+A42+1 -> 37 | B43: Mounjaro | C43: LLY | F43: US launch 6/2022. First reported quarter Q222 | G43: =SUM(AK43:GH43) -> 7453 | I43: =SUM(AK43:AN43) -> 1051 | J43: =SUM(AO43:AR43) -> 6402 | K43: =SUM(AS43:AV43) -> 0 | L43: =SUM(AW43:AZ43) -> 0 | M43: =SUM(BA43:BD43) -> 0 | N43: =SUM(BE43:BH43) -> 0 | O43: =SUM(BI43:BL43) -> 0 | P43: =SUM(BM43:BP43) -> 0 | Q43: =SUM(BQ43:BT43) -> 0 | R43: =SUM(BU43:BX43) -> 0 | S43: =SUM(BY43:CB43) -> 0 | T43: =SUM(CC43:CF43) -> 0 | AK43: 16 | AL43: 187.3 | AM43: 279.2 | AN43: 568.5 | AO43: 980 | AP43: 1409 | AQ43: 2206 | AR43: 1807
A44: =+A43+1 -> 38 | B44: Kisqali | C44: NVS | G44: =SUM(AK44:GH44) -> 7070 | I44: =SUM(AK44:AN44) -> 76 | J44: =SUM(AO44:AR44) -> 235 | K44: =SUM(AS44:AV44) -> 480 | L44: =SUM(AW44:AZ44) -> 687 | M44: =SUM(BA44:BD44) -> 937 | N44: =SUM(BE44:BH44) -> 1231 | O44: =SUM(BI44:BL44) -> 2080 | P44: =SUM(BM44:BP44) -> 1344 | Q44: =SUM(BQ44:BT44) -> 0 | R44: =SUM(BU44:BX44) -> 0 | S44: =SUM(BY44:CB44) -> 0 | T44: =SUM(CC44:CF44) -> 0 | AK44: 7 | AL44: 8 | AM44: 26 | AN44: 35 | AO44: 44 | AP44: 59 | AQ44: 72 | AR44: 60 | AS44: 91 | AT44: 111 | AU44: 123 | AV44: 155 | AW44: 161 | AX44: 159 | AY44: 183 | AZ44: 184 | BA44: 195 | BB44: 225 | BC44: 232 | BD44: 285 | BE44: 239 | BF44: 308 | BG44: 327 | BH44: 357 | BI44: 415 | BJ44: 493 | BK44: 562 | BL44: 610 | BM44: 627 | BN44: 717
A45: =+A44+1 -> 39 | B45: Cyramza | C45: LLY | G45: =SUM(AK45:GH45) -> 6852.5 | I45: =SUM(AK45:AN45) -> 143.2 | J45: =SUM(AO45:AR45) -> 447.4 | K45: =SUM(AS45:AV45) -> 654.3 | L45: =SUM(AW45:AZ45) -> 770.7 | M45: =SUM(BA45:BD45) -> 836.1 | N45: =SUM(BE45:BH45) -> 965.9 | O45: =SUM(BI45:BL45) -> 1034.1 | P45: =SUM(BM45:BP45) -> 1022.8 | Q45: =SUM(BQ45:BT45) -> 978 | R45: =SUM(BU45:BX45) -> 0 | S45: =SUM(BY45:CB45) -> 0 | T45: =SUM(CC45:CF45) -> 0 | AK45: 13.7 | AL45: 28.4 | AM45: 33.6 | AN45: 67.5 | AO45: 87.7 | AP45: 111.2 | AQ45: 117.5 | AR45: 131 | AS45: 147 | AT45: 159 | AU45: 177.1 | AV45: 171.2 | AW45: 186.3 | AX45: 196 | AY45: 204.8 | AZ45: 183.6 | BA45: 218.8 | BB45: 198.4 | BC45: 220.6 | BD45: 198.3 | BE45: 241.8 | BF45: 240 | BG45: 245.1 | BH45: 239 | BI45: 256.7 | BJ45: 252.7 | BK45: 284.2 | BL45: 240.5 | BM45: 268.7 | BN45: 253.4 | BO45: 270.4 | BP45: 230.3 | BQ45: 231.3 | BR45: 232.1 | BS45: 277.8 | BT45: 236.8
A46: =+A45+1 -> 40 | B46: Verzenio | C46: LLY | G46: =SUM(AK46:GH46) -> 6352.6 | I46: =SUM(AK46:AN46) -> 192.9 | J46: =SUM(AO46:AR46) -> 483.6 | K46: =SUM(AS46:AV46) -> 810.1 | L46: =SUM(AW46:AZ46) -> 1227.4 | M46: =SUM(BA46:BD46) -> 2079.7 | N46: =SUM(BE46:BH46) -> 1558.9 | O46: =SUM(BI46:BL46) -> 0 | AK46: 21 | AL46: 29.7 | AM46: 57.7 | AN46: 84.5 | AO46: 83.1 | AP46: 109.4 | AQ46: 133.9 | AR46: 157.2 | AS46: 179.1 | AT46: 188 | AU46: 208.6 | AV46: 234.4 | AW46: 281.6 | AX46: 269 | AY46: 341.3 | AZ46: 335.5 | BA46: 404.1 | BB46: 469.4 | BC46: 588.5 | BD46: 617.7 | BE46: 808 | BF46: 750.9
A47: =+A46+1 -> 41 | B47: Zolgensma | C47: NVS | G47: =SUM(AK47:GH47) -> 5845 | I47: =SUM(AK47:AN47) -> 721 | J47: =SUM(AO47:AR47) -> 1179 | K47: =SUM(AS47:AV47) -> 1459 | L47: =SUM(AW47:AZ47) -> 1248 | M47: =SUM(BA47:BD47) -> 1238 | N47: =SUM(BE47:BH47) -> 0 | O47: =SUM(BI47:BL47) -> 0 | AK47: 160 | AL47: 186 | AM47: 170 | AN47: 205 | AO47: 291 | AP47: 254 | AQ47: 319 | AR47: 315 | AS47: 375 | AT47: 342 | AU47: 363 | AV47: 379 | AW47: 319 | AX47: 309 | AY47: 309 | AZ47: 311 | BA47: 308 | BB47: 286 | BC47: 295 | BD47: 349
A48: =+A47+1 -> 42 | B48: Basaglar | C48: LLY | G48: =SUM(AK48:GH48) -> 5220.3 | I48: =SUM(AK48:AN48) -> 38.3 | J48: =SUM(AO48:AR48) -> 191.5 | K48: =SUM(AS48:AV48) -> 667.3 | L48: =SUM(AW48:AZ48) -> 975.5 | M48: =SUM(BA48:BD48) -> 1164.5 | N48: =SUM(BE48:BH48) -> 987.6 | O48: =SUM(BI48:BL48) -> 800.9 | AK48: 3.8 | AL48: 7.3 | AM48: 10.9 | AN48: 16.3 | AO48: 19.4 | AP48: 39.5 | AQ48: 46 | AR48: 86.6 | AS48: 145.7 | AT48: 153.8 | AU48: 166 | AV48: 201.8 | AW48: 201.2 | AX48: 232.2 | AY48: 251.4 | AZ48: 290.7 | BA48: 263.2 | BB48: 307.2 | BC48: 303.7 | BD48: 290.4 | BE48: 248.2 | BF48: 282.1 | BG48: 246.6 | BH48: 210.7 | BI48: 192.8 | BJ48: 242.4 | BK48: 191.5 | BL48: 174.2 | BM48: 193 | BN48: 201.7
A49: =+A48+1 -> 43 | B49: Kesmipta | C49: NVS | G49: =SUM(AK49:GH49) -> 5086 | I49: =SUM(AK49:AN49) -> 131 | J49: =SUM(AO49:AR49) -> 690 | K49: =SUM(AS49:AV49) -> 1531 | L49: =SUM(AW49:AZ49) -> 2734 | M49: =SUM(BA49:BD49) -> 0 | N49: =SUM(BE49:BH49) -> 0 | O49: =SUM(BI49:BL49) -> 0 | AK49: 1 | AL49: 14 | AM49: 50 | AN49: 66 | AO49: 109 | AP49: 147 | AQ49: 195 | AR49: 239 | AS49: 289 | AT49: 369 | AU49: 384 | AV49: 489 | AW49: 657 | AX49: 641 | AY49: 637 | AZ49: 799
A50: =+A49+1 -> 44 | B50: Olumiant | C50: LLY | G50: =SUM(AK50:GH50) -> 3488.8 | I50: =SUM(AK50:AN50) -> 45.9 | J50: =SUM(AO50:AR50) -> 202.6 | K50: =SUM(AS50:AV50) -> 426.9 | L50: =SUM(AW50:AZ50) -> 638.9 | M50: =SUM(BA50:BD50) -> 1115.1 | N50: =SUM(BE50:BH50) -> 830.5 | O50: =SUM(BI50:BL50) -> 228.9 | AK50: 1.9 | AL50: 4.8 | AM50: 16.2 | AN50: 23 | AO50: 32.2 | AP50: 44.7 | AQ50: 55.6 | AR50: 70.1 | AS50: 82.1 | AT50: 102.4 | AU50: 114.6 | AV50: 127.8 | AW50: 139.7 | AX50: 145 | AY50: 162 | AZ50: 192.2 | BA50: 193.8 | BB50: 208.4 | BC50: 406.9 | BD50: 306 | BE50: 255.6 | BF50: 186.2 | BG50: 182.9 | BH50: 205.8 | BI50: 228.9
A51: =+A50+1 -> 45 | B51: Effient | C51: LLY | G51: =SUM(AK51:GH51) -> 2990.3 | I51: =SUM(AK51:AN51) -> 58.3 | J51: =SUM(AO51:AR51) -> 211.3 | K51: =SUM(AS51:AV51) -> 401.2 | L51: =SUM(AW51:AZ51) -> 483.6 | M51: =SUM(BA51:BD51) -> 508.4 | N51: =SUM(BE51:BH51) -> 519.9 | O51: =SUM(BI51:BL51) -> 539 | AK51: 22.6 | AL51: 4 | AM51: 8.8 | AN51: 22.9 | AO51: 36.3 | AP51: 47 | AQ51: 56.3 | AR51: 71.7 | AS51: 83.5 | AT51: 90.9 | AU51: 115.8 | AV51: 111 | AW51: 109.7 | AX51: 120.6 | AY51: 115.9 | AZ51: 137.4 | BA51: 124.9 | BB51: 130.6 | BC51: 119.3 | BD51: 133.6 | BE51: 131.5 | BF51: 137.8 | BG51: 121.8 | BH51: 128.8 | BI51: 132.1 | BJ51: 140.3 | BK51: 131.5 | BL51: 135.1 | BM51: 127.7 | BN51: 140.9
A52: =+A51+1 -> 46 | B52: Byetta | C52: LLY | G52: =SUM(AK52:GH52) -> 2345.5313 | I52: =SUM(AK52:AN52) -> 175.7 | J52: =SUM(AO52:AR52) -> 379.93134 | K52: =SUM(AS52:AV52) -> 385.2 | L52: =SUM(AW52:AZ52) -> 430.9 | M52: =SUM(BA52:BD52) -> 445.8 | N52: =SUM(BE52:BH52) -> 417.7 | O52: =SUM(BI52:BL52) -> 110.3 | AK52: 25.7 | AL52: 36 | AM52: 52 | AN52: 62 | AO52: =AS52/1.34 -> 68.731343 | AP52: 72 | AQ52: 152.1 | AR52: 87.1 | AS52: 92.1 | AT52: 82.7 | AU52: 101.2 | AV52: 109.2 | AW52: 103 | AX52: 97.5 | AY52: 114.6 | AZ52: 115.8 | BA52: 120.5 | BB52: 115.7 | BC52: 106.9 | BD52: 102.7 | BE52: 105.3 | BF52: 101.8 | BG52: 103.9 | BH52: 106.7 | BI52: 110.3
A53: =+A52+1 -> 47 | B53: Zepbound | C53: LLY | G53: =SUM(AK53:GH53) -> 1936 | I53: =SUM(AK53:AN53) -> 1936 | J53: =SUM(AO53:AR53) -> 0 | K53: =SUM(AS53:AV53) -> 0 | L53: =SUM(AW53:AZ53) -> 0 | M53: =SUM(BA53:BD53) -> 0 | N53: =SUM(BE53:BH53) -> 0 | O53: =SUM(BI53:BL53) -> 0 | AK53: 176 | AL53: 517 | AM53: 1243
A54: =+A53+1 -> 48 | B54: Emgality | C54: LLY | G54: =SUM(AK54:GH54) -> 1912.7 | I54: =SUM(AK54:AN54) -> 101.1 | J54: =SUM(AO54:AR54) -> 319.2 | K54: =SUM(AS54:AV54) -> 525.7 | L54: =SUM(AW54:AZ54) -> 636.8 | M54: =SUM(BA54:BD54) -> 329.9 | N54: =SUM(BE54:BH54) -> 0 | O54: =SUM(BI54:BL54) -> 0 | AK54: 4.9 | AL54: 14.2 | AM54: 34.3 | AN54: 47.7 | AO54: 66.3 | AP54: 74 | AQ54: 87.4 | AR54: 91.5 | AS54: 109.9 | AT54: 119.5 | AU54: 156.3 | AV54: 140 | AW54: 161.5 | AX54: 149.3 | AY54: 157.5 | AZ54: 168.5 | BA54: 175.6 | BB54: 154.3
A55: =+A54+1 -> 49 | B55: Pluvicto | C55: NVS | G55: =SUM(AK55:GH55) -> 1906 | I55: =SUM(AK55:AN55) -> 271 | J55: =SUM(AO55:AR55) -> 980 | K55: =SUM(AS55:AV55) -> 655 | L55: =SUM(AW55:AZ55) -> 0 | M55: =SUM(BA55:BD55) -> 0 | N55: =SUM(BE55:BH55) -> 0 | O55: =SUM(BI55:BL55) -> 0 | AK55: 2 | AL55: 10 | AM55: 80 | AN55: 179 | AO55: 211 | AP55: 240 | AQ55: 256 | AR55: 273 | AS55: 310 | AT55: 345
A56: =+A55+1 -> 50 | B56: Piqray | C56: NVS | G56: =SUM(AK56:GH56) -> 1866 | I56: =SUM(AK56:AN56) -> 263 | J56: =SUM(AO56:AR56) -> 327 | K56: =SUM(AS56:AV56) -> 327 | L56: =SUM(AW56:AZ56) -> 461 | M56: =SUM(BA56:BD56) -> 488 | N56: =SUM(BE56:BH56) -> 0 | O56: =SUM(BI56:BL56) -> 0 | AK56: 43 | AL56: 67 | AM56: 74 | AN56: 79 | AO56: 83 | AP56: 84 | AQ56: 78 | AR56: 82 | AS56: 82 | AT56: 87 | AU56: 73 | AV56: 85 | AW56: 103 | AX56: 112 | AY56: 116 | AZ56: 130 | BA56: 128 | BB56: 131 | BC56: 109 | BD56: 120
A57: =+A56+1 -> 51 | B57: Mayzent | C57: NVS | G57: =SUM(AK57:GH57) -> 1221 | I57: =SUM(AK57:AN57) -> 85 | J57: =SUM(AO57:AR57) -> 230 | K57: =SUM(AS57:AV57) -> 321 | L57: =SUM(AW57:AZ57) -> 376 | M57: =SUM(BA57:BD57) -> 209 | N57: =SUM(BE57:BH57) -> 0 | O57: =SUM(BI57:BL57) -> 0 | AK57: 4 | AL57: 17 | AM57: 30 | AN57: 34 | AO57: 49 | AP57: 57 | AQ57: 55 | AR57: 69 | AS57: 76 | AT57: 81 | AU57: 79 | AV57: 85 | AW57: 94 | AX57: 99 | AY57: 89 | AZ57: 94 | BA57: 103 | BB57: 106
A58: =+A57+1 -> 52 | B58: Tyvyt | C58: LLY | G58: =SUM(AK58:GH58) -> 1215.2 | I58: =SUM(AK58:AN58) -> 134 | J58: =SUM(AO58:AR58) -> 308.7 | K58: =SUM(AS58:AV58) -> 418.1 | L58: =SUM(AW58:AZ58) -> 293.4 | M58: =SUM(BA58:BD58) -> 61 | N58: =SUM(BE58:BH58) -> 0 | O58: =SUM(BI58:BL58) -> 0 | AK58: 9.9 | AL58: 40.1 | AM58: 46.6 | AN58: 37.4 | AO58: 57.4 | AP58: 64.1 | AQ58: 84.4 | AR58: 102.8 | AS58: 109.7 | AT58: 105 | AU58: 125.6 | AV58: 77.8 | AW58: 85.5 | AX58: 73.6 | AY58: 76.8 | AZ58: 57.5 | BA58: 61
A59: =+A58+1 -> 53 | B59: Aimovig | C59: NVS | G59: =SUM(AK59:GH59) -> 1127 | I59: =SUM(AK59:AN59) -> 83 | J59: =SUM(AO59:AR59) -> 136 | K59: =SUM(AS59:AV59) -> 212 | L59: =SUM(AW59:AZ59) -> 218 | M59: =SUM(BA59:BD59) -> 256 | N59: =SUM(BE59:BH59) -> 222 | O59: =SUM(BI59:BL59) -> 0 | AK59: 8 | AL59: 18 | AM59: 24 | AN59: 33 | AO59: 28 | AP59: 36 | AQ59: 33 | AR59: 39 | AS59: 56 | AT59: 47 | AU59: 53 | AV59: 56 | AW59: 59 | AX59: 54 | AY59: 55 | AZ59: 50 | BA59: 59 | BB59: 61 | BC59: 67 | BD59: 69 | BE59: 69 | BF59: 76 | BG59: 77
A60: =+A59+1 -> 54 | B60: Scemblix | C60: NVS | G60: =SUM(AK60:GH60) -> 869 | I60: =SUM(AK60:AN60) -> 104 | J60: =SUM(AO60:AR60) -> 340 | K60: =SUM(AS60:AV60) -> 425 | L60: =SUM(AW60:AZ60) -> 0 | M60: =SUM(BA60:BD60) -> 0 | N60: =SUM(BE60:BH60) -> 0 | O60: =SUM(BI60:BL60) -> 0 | AK60: 7 | AL60: 25 | AM60: 31 | AN60: 41 | AO60: 52 | AP60: 76 | AQ60: 106 | AR60: 106 | AS60: 125 | AT60: 136 | AU60: 164
A61: =+A60+1 -> 55 | B61: Leqvio | C61: NVS | G61: =SUM(AK61:GH61) -> 812 | I61: =SUM(AK61:AN61) -> 12 | J61: =SUM(AO61:AR61) -> 112 | K61: =SUM(AS61:AV61) -> 355 | L61: =SUM(AW61:AZ61) -> 333 | M61: =SUM(BA61:BD61) -> 0 | N61: =SUM(BE61:BH61) -> 0 | O61: =SUM(BI61:BL61) -> 0 | AK61: 1 | AL61: 2 | AM61: 5 | AN61: 4 | AO61: 14 | AP61: 22 | AQ61: 34 | AR61: 42 | AS61: 64 | AT61: 78 | AU61: 90 | AV61: 123 | AW61: 151 | AX61: 182
A62: =+A61+1 -> 56 | B62: Beovu | C62: NVS | G62: =SUM(AK62:GH62) -> 765 | I62: =SUM(AK62:AN62) -> 188 | J62: =SUM(AO62:AR62) -> 172 | K62: =SUM(AS62:AV62) -> 205 | L62: =SUM(AW62:AZ62) -> 200 | M62: =SUM(BA62:BD62) -> 0 | N62: =SUM(BE62:BH62) -> 0 | O62: =SUM(BI62:BL62) -> 0 | AK62: 35 | AL62: 68 | AM62: 34 | AN62: 51 | AO62: 37 | AP62: 39 | AQ62: 47 | AR62: 49 | AS62: 51 | AT62: 48 | AU62: 54 | AV62: 52 | AW62: 49 | AX62: 51 | AY62: 53 | AZ62: 47
A63: =+A62+1 -> 57 | B63: Adakveo | C63: NVS | G63: =SUM(AK63:GH63) -> 658 | I63: =SUM(AK63:AN63) -> 105 | J63: =SUM(AO63:AR63) -> 164 | K63: =SUM(AS63:AV63) -> 194 | L63: =SUM(AW63:AZ63) -> 195 | M63: =SUM(BA63:BD63) -> 0 | N63: =SUM(BE63:BH63) -> 0 | O63: =SUM(BI63:BL63) -> 0 | AK63: 15 | AL63: 21 | AM63: 35 | AN63: 34 | AO63: 37 | AP63: 42 | AQ63: 42 | AR63: 43 | AS63: 44 | AT63: 49 | AU63: 50 | AV63: 51 | AW63: 52 | AX63: 53 | AY63: 45 | AZ63: 45
A64: =+A63+1 -> 58 | B64: Tabrecta | C64: NVS | G64: =SUM(AK64:GH64) -> 412 | I64: =SUM(AK64:AN64) -> 52 | J64: =SUM(AO64:AR64) -> 104 | K64: =SUM(AS64:AV64) -> 138 | L64: =SUM(AW64:AZ64) -> 118 | M64: =SUM(BA64:BD64) -> 0 | N64: =SUM(BE64:BH64) -> 0 | O64: =SUM(BI64:BL64) -> 0 | AK64: 6 | AL64: 12 | AM64: 17 | AN64: 17 | AO64: 22 | AP64: 24 | AQ64: 27 | AR64: 31 | AS64: 30 | AT64: 36 | AU64: 36 | AV64: 36 | AW64: 41 | AX64: 36 | AY64: 41
A65: =+A64+1 -> 59 | B65: Retevmo | C65: LLY | G65: =SUM(AK65:GH65) -> 394.6 | I65: =SUM(AK65:AN65) -> 53.4 | J65: =SUM(AO65:AR65) -> 139.7 | K65: =SUM(AS65:AV65) -> 201.5 | L65: =SUM(AW65:AZ65) -> 0 | M65: =SUM(BA65:BD65) -> 0 | N65: =SUM(BE65:BH65) -> 0 | O65: =SUM(BI65:BL65) -> 0 | AK65: 6.3 | AL65: 11.6 | AM65: 18.7 | AN65: 16.8 | AO65: 25.7 | AP65: 33.6 | AQ65: 38.6 | AR65: 41.8 | AS65: 45 | AT65: 40.5 | AU65: 64.6 | AV65: 51.4
A66: =+A65+1 -> 60 | B66: Fabhalta | C66: NVS | G66: =SUM(AK66:GH66) -> 28 | I66: =SUM(AK66:AN66) -> 28 | J66: =SUM(AO66:AR66) -> 0 | K66: =SUM(AS66:AV66) -> 0 | L66: =SUM(AW66:AZ66) -> 0 | M66: =SUM(BA66:BD66) -> 0 | N66: =SUM(BE66:BH66) -> 0 | O66: =SUM(BI66:BL66) -> 0 | AK66: 6 | AL66: 22
B71: DKK | C71: 6.86
B78: Eliquis US | C78: BMY | D78: Cardiovascular | E78: 3 | G78: =SUM(AK78:EV78) -> 76424 | I78: 146 | J78: 774 | K78: 1860 | L78: 3343 | M78: 4872 | N78: 6438 | O78: 7929 | P78: =SUM(BM78:BP78) -> 8933 | Q78: =SUM(BQ78:BT78) -> 10360 | R78: =SUM(BU78:BX78) -> 11772 | S78: =SUM(BY78:CB78) -> 12020 | T78: =SUM(CC78:CF78) -> 10010 | U78: =SUM(CG78:CJ78) -> 0 | V78: =SUM(CK78:CN78) -> 0 | AK78: 1 | AL78: 22 | AM78: 12 | AN78: 41 | AO78: 71 | AP78: 106 | AQ78: 171 | AR78: 216 | AS78: 281 | AT78: 355 | AU78: 437 | AV78: 466 | AW78: 602 | AX78: 734 | AY78: 777 | AZ78: 884 | BA78: 948 | BB78: 1101 | BC78: 1176 | BD78: 1232 | BE78: 1363 | BF78: 1506 | BG78: 1650 | BH78: 1577 | BI78: 1705 | BJ78: 1925 | BK78: 2042 | BL78: 1928 | BM78: 2034 | BN78: 2641 | BO78: 2163 | BP78: 2095 | BQ78: 2269 | BR78: 2886 | BS78: 2792 | BT78: 2413 | BU78: 2671 | BV78: 3211 | BW78: 3235 | BX78: 2655 | BY78: 2688 | BZ78: 3423 | CA78: 3204 | CB78: 2705 | CC78: 2874 | CD78: 3720 | CE78: 3416
B79: Eliquis ROW | C79: PFE | D79: Cardiovascular | E79: 3 | G79: =SUM(AK79:EV79) -> 42355 | I79: =SUM(AK79:AN79) -> 266 | J79: =SUM(AO79:AR79) -> 788 | K79: =SUM(AS79:AV79) -> 1400 | L79: =SUM(AW79:AZ79) -> 1662 | M79: =SUM(BA79:BD79) -> 2523 | N79: =SUM(BE79:BH79) -> 3434 | O79: =SUM(BI79:BL79) -> 4220 | P79: =SUM(BM79:BP79) -> 4948 | Q79: =SUM(BQ79:BT79) -> 5970 | R79: =SUM(BU79:BX79) -> 6481 | S79: =SUM(BY79:CB79) -> 6746 | T79: =SUM(CC79:CF79) -> 3917 | U79: =SUM(CG79:CJ79) -> 0 | V79: =SUM(CK79:CN79) -> 0 | AK79: 37 | AL79: 57 | AM79: 75 | AN79: 97 | AO79: 137 | AP79: 177 | AQ79: 217 | AR79: 257 | AS79: 300 | AT79: 350 | AU79: 350 | AV79: 400 | AW79: 354 | AX79: 371 | AY79: 449 | AZ79: 488 | BA79: 564 | BB79: 605 | BC79: 644 | BD79: 710 | BE79: 765 | BF79: 889 | BG79: 870 | BH79: 910 | BI79: 1011 | BJ79: 1085 | BK79: 1025 | BL79: 1099 | BM79: 1300 | BN79: 1272 | BO79: 1114 | BP79: 1262 | BQ79: 1643 | BR79: 1481 | BS79: 1346 | BT79: 1500 | BU79: 1793 | BV79: 1745 | BW79: 1464 | BX79: 1479 | BY79: 1874 | BZ79: 1762 | CA79: 1498 | CB79: 1612 | CC79: 2040 | CD79: 1877
B80: Januvia | C80: MRK | D80: Diabetes | E80: 1 | G80: =SUM(AK80:GH80) -> 49414 | I80: =SUM(AK80:AN80) -> 458 | J80: =SUM(AO80:AR80) -> 1185 | K80: =SUM(AS80:AV80) -> 1364 | L80: =SUM(AW80:AZ80) -> 2269 | M80: =SUM(BA80:BD80) -> 3039 | N80: =SUM(BE80:BH80) -> 3912 | O80: =SUM(BI80:BL80) -> 4017 | P80: =SUM(BM80:BP80) -> 3970 | Q80: =SUM(BQ80:BT80) -> 4024 | R80: =SUM(BU80:BX80) -> 3897 | S80: =SUM(BY80:CB80) -> 3731 | T80: =SUM(CC80:CF80) -> 3694 | U80: =SUM(CG80:CJ80) -> 3469 | V80: =SUM(CK80:CN80) -> 3392 | AK80: 42 | AL80: 87 | AM80: 144 | AN80: 185 | AO80: 200 | AP80: 272 | AQ80: 334 | AR80: 379 | AT80: 411 | AU80: 462 | AV80: 491 | AW80: 558 | AX80: 511 | AY80: 600 | AZ80: 600 | BA80: 675 | BB80: 739 | BC80: 779 | BD80: 846 | BE80: 960 | BF80: 919 | BG80: 1058 | BH80: 975 | BI80: 1134 | BJ80: 884 | BK80: 1072 | BL80: 927 | BM80: 1121 | BN80: 858 | BO80: 1058 | BP80: 933 | BQ80: 1082 | BR80: 884 | BS80: 1044 | BT80: 1014 | BU80: 921 | BV80: 906 | BW80: 1064 | BX80: 1006 | BY80: 932 | BZ80: 839 | CA80: 948 | CB80: 1012 | CC80: 938 | CD80: 880 | CE80: 949 | CF80: 927 | CG80: 930 | CH80: 824 | CI80: 908 | CJ80: 807 | CK80: 943 | CL80: 774 | CM80: 854 | CN80: 821 | CO80: 857 | CP80: 809 | CQ80: 784 | CR80: 852 | CS80: 878 | CT80: 779 | CU80: 756 | CV80: 717 | CW80: 561
B81: Janumet | C81: MRK | D81: Diabetes | E81: 1 | G81: =SUM(AK81:GH81) -> 25362.5 | I81: =SUM(AK81:AN81) -> 131 | J81: =SUM(AO81:AR81) -> 415.5 | K81: =SUM(AS81:AV81) -> 731 | L81: =SUM(AW81:AZ81) -> 1058 | M81: =SUM(BA81:BD81) -> 1449 | N81: =SUM(BE81:BH81) -> 1677 | O81: =SUM(BI81:BL81) -> 1895 | P81: =SUM(BM81:BP81) -> 2103 | Q81: =SUM(BQ81:BT81) -> 2148 | R81: =SUM(BU81:BX81) -> 2190 | S81: =SUM(BY81:CB81) -> 2206 | T81: =SUM(CC81:CF81) -> 2213 | U81: =SUM(CG81:CJ81) -> 2014 | V81: =SUM(CK81:CN81) -> 1954 | AK81: 24 | AL81: 19 | AM81: 30 | AN81: 58 | AO81: 72 | AP81: 101 | AQ81: =AVERAGE(AP81,AR81) -> 114.5 | AR81: 128 | AS81: 155 | AT81: 173 | AU81: 202 | AV81: 201 | AW81: 218 | AX81: 247 | AY81: 288 | AZ81: 305 | BA81: 321 | BB81: 350 | BC81: 386 | BD81: 392 | BE81: 411 | BF81: 405 | BG81: 452 | BH81: 409 | BI81: 474 | BJ81: 442 | BK81: 503 | BL81: 476 | BM81: 519 | BN81: 505 | BO81: 570 | BP81: 509 | BQ81: 554 | BR81: 562 | BS81: 526 | BT81: 506 | BU81: 569 | BV81: 548 | BW81: 577 | BX81: 496 | BY81: 563 | BZ81: 513 | CA81: 586 | CB81: 544 | CC81: 585 | CD81: 563 | CE81: 535 | CF81: 530 | CG81: 533 | CH81: 503 | CI81: 475 | CJ81: 503 | CK81: 490 | CL81: 506 | CM81: 472 | CN81: 486 | CO81: 477 | CP81: 487 | CQ81: 514 | CR81: 454 | CS81: 476 | CT81: 417 | CU81: 353

Sheet China
C2: Name
A3: x | B3: =Acquisitions!A14+1 -> 1 | C3: Jiangsu Hengrui | D3: 600276 CH
B4: =Main!D43+1 -> 34 | C4: Zhangzhou Pientzehuang | D4: 600436 CH
A5: x | B5: =Main!D32+1 -> 23 | C5: Chongqing Zhifei | D5: 300122 CH
B6: =B5+1 -> 24 | C6: Changchun High Tech | D6: 000661 CH
B7: =B6+1 -> 25 | C7: Huadong Medicine | D7: 000963 CH
B8: =Main!D54+1 -> 43 | C8: Walvax Biotech | D8: 300142 CH
B9: =B8+1 -> 44 | C9: Beijing Tongren | D9: 600085 CH
A10: x | B10: =B9+1 -> 45 | C10: Yunnan Baiyao | D10: 000538 CH
C11: Shanghai Pharma | D11: 601607 CH
C12: Sichuan Kelun | D12: 002422 CH | E12: 27.98 | F12: {=40290/CNY} -> 5682.6516
C13: Beijing Wantai | D13: 603392 CH
C15: Zhejiang Nhu | D15: 002001 CH

Sheet FX
A1: Main
B2: USD/DKK | C2: 7.057
B3: USD/CHF | C3: 0.91
B4: EUR/USD | C4: 1.11
B5: AUD/USD | C5: 0.67
B6: GBP/USD | C6: 1.3
B7: USD/JPY | C7: 145.25
B8: USD/HKD | C8: 7.8
B9: KRW/USD | C9: 1433
B10: USD/INR | C10: 82.55
B11: USD/CNY | C11: 7.09

Sheet Private
A1: Main
B2: Name | C2: Founded | D2: HQ | E2: Round | F2: Size | G2: Investors | H2: Date | I2: Notes | J2: Valuation
B3: Altos | E3: Series A | F3: 3000 | G3: ARCH, Bezos
B4: ElevateBio | E4: Series D | F4: 401 | G4: Matrix, Softbank, Surveyor, Redmile, Novo Nordisk, Fidelity, EcoR1, Samsara | H4: 45070
B5: Insitro | C5: 2018 | D5: South San Francisco, CA | E5: Series C | F5: 400
B6: Areteia Therapeutics | E6: Series A | F6: 350 | G6: Bain, Saturn | H6: 44754
B7: Tessera Therapeutics | C7: 2018 | E7: Series C | F7: 300 | G7: Softbank | J7: 1700
B8: Metsera | E8: Series A | F8: 290 | G8: ARCH, SoftBank | H8: 45400
B9: ArsenalBio | E9: Series B | F9: 221 | G9: Softbank | H9: 44670
B10: XtalPi
B11: Biosplice Therapeutics
B12: Abogen Biosciences | C12: 2019 | I12: Chinese RNA
B13: Mojave Pharma
B14: Laronde
B15: Kallyope
B16: Kriya Therapeutics | E16: Series C | F16: 270 | G16: Patient Square Capital | H16: 44697
B17: Genor Biopharma
B18: Insilico Medicine | E18: Series C | F18: 259
B19: Metis Pharmaceuticals | C19: 2020 | E19: Series B | F19: 150 | H19: 44657 | I19: Chinese
B20: Generate Biomedicines
B21: Affinia Therapeutics | E21: Series B | F21: 110
B22: RayzeBio | C22: 2018 | E22: Series D | F22: 160 | G22: Sofinnova, Viking, Wellington | H22: 44817 | I22: Radiopharma
B23: RayzeBio | C23: 2018 | E23: Series C | F23: 108 | G23: Venrock | H23: 44362
B24: RayzeBio | C24: 2018 | E24: Series B | F24: 105 | G24: Venrock | H24: 44173
B25: RayzeBio | C25: 2018 | E25: Series A | F25: 45 | G25: venBio, Versant | H25: 44118
B27: FogPharma | E27: Series E | F27: 145 | G27: Nextech, venBio | H27: 45352
B28: FogPharma | E28: Series D | F28: 178 | G28: Zhejiang, venBio, T Rowe, Invus | H28: 44886
B29: FogPharma | E29: Series C | F29: 107 | I29: Beta-Catenin
B31: Ventus Therapeutics | E31: Series C | F31: 140 | G31: Softbank, RA | H31: 44601
B32: Merida Biosciences | E32: Series A | F32: 121 | G32: Bain, BVF, Third Rock | H32: 45756
B33: Comanche Biopharma | E33: Series B | F33: 75 | G33: NEA | H33: 45308
B34: Accent Therapeutics | E34: Series C | F34: 75 | G34: Mirae | H34: 45314
B35: Alumis
B36: Odyssey Therapeutics
B37: Maze Therapeutics
B38: TauRx Pharmaceuticals
B39: Vividion Therapeutics
B40: Tizona Therapeutics
B41: Charm Therapeutics | C41: 2021 | F41: 20 | H41: 45030
B42: Pathos | C42: 2020 | F42: 20 | H42: 44987
B43: Aqemia
B44: Mindrank | C44: 44188 | F44: 19 | H44: 44545
B45: Pelage Pharma | E45: Series A | F45: 16.8 | G45: Google | H45: 45349
B46: Tubulis
B47: Granata Bio | E47: Series A | F47: 14 | G47: Google, Alumni | H47: 45307
B48: Alto Neuroscience
B49: Eureka Therapeutics
B50: Affinivax
B51: Pionyr Immunotherapeutics
B52: Grey Wolf Therapeutics
B53: Idrx | E53: Series B | F53: 120 | H53: 45511
B54: Elicio Therapeutics
B55: Amolyt Pharma
B56: Ribon Therapeutics
B57: Avalyn | C57: 45196 | E57: Series C | F57: 175 | G57: Perceptive, SR One, Eventide, Vida Ventures, Wellington, Rock Springs, T. Rowe, Surveyor Capital, Catalio
B58: Atomwise
B59: Nimbus
B60: Acelyrin
B61: Eikon Therapeutics | E61: Series B | F61: 500
B62: Akamis Bio
B63: Structure Therapeutics
B64: Treeline Biosciences
B65: Tmunity Therapeutics
B66: Scribe Therapeutics
B67: Orna Therapeutics
B68: Remix Therapeutics
B69: Arch Oncology
B70: A2 Biotherapeutics
B71: Gilgamesh Pharmaceuticals
B72: Capsida
B73: Carisma Therapeutics
... B79: Dyno Therapeutics
B80: BigHat Biosciences | E80: Series B | F80: 75m
B81: Genesis Biomedicines | E81: Series A | F81: 52m
B82: Shape Therapeutics
B83: Alloy Therapeutics
B84: Goldfinch Biopharma
B85: Evozyne
B86: ReCode Therapeutics
B87: Exarta
B88: Affilogic
B89: Faeth Therapeutics
B90: Manifold Bio | C90: 2019 | D90: Boston, MA
B91: Avista Therapeutics
B92: InnoRNA
B93: Empirico
B94: 1859, Inc. | C94: 2019 | D94: San Diego, CA | E94: Series A | F94: 40m | G94: Northpond Ventures, OMX Ventures | H94: 44599
B95: SyntheticGestalt | E95: Series A | F95: 11m
B96: Neomorph
B97: Moonwalk
B98: Moonlake Immunotherapeutics | I98: IL-17 A/F mab
B99: Meissa Vaccines
B100: Wren Therapeutics | C100: 2019? | E100: Series A | F100: 18m GBP | H100: 43466 | I100: Alzheimer's amyloid aggregation inhibitor
B101: Aria Pharmaceuticals
B103: Cellarity | E103: Series C | F103: 121
B104: Abyssinia Biologics
B105: Intima Bioscience
B106: Noema Pharma
B107: Microgen | I107: Microgen.ru
B108: Metagenomi
...

Sheet Funds
A1: Main
B2: Name | C2: Founder | D2: Type | E2: ADV | F2: 13F
B3: Baker Brothers | C3: Felix & Julian Baker | D3: Public Long-Only | E3: 21976.24 | F3: 7825
B4: Orbimed | D4: Mixed | E4: 18211.07
B5: Deerfield | D5: Mixed | E5: 16117.395
B6: RA Capital | C6: Peter Kolchinsky | D6: Venture, Hedge | E6: 11227.234
B7: Perceptive | D7: Mixed | E7: 9575.682
B8: RTW | C8: Rod Wong | D8: Venture, Hedge, Royalty | E8: 8820.4851
B9: Avoro | E9: 8737.9044
B10: Citadel | C10: Ken Griffin | D10: Hedge Fund | F10: 6000
B11: Armistice | C11: Steve Boyd | D11: Hedge Fund | E11: 5911.15
B12: Rock Springs | E12: 5768.7178
B13: Millennium | C13: Israel Englander | D13: Hedge Fund | F13: 5600
B14: Deep Track | E14: 5116.08
B15: EcoR1 | E15: 5001.7414
B16: Braidwell | C16: Alex Karnal | E16: 4902.193 | F16: 3187.7679
B17: Cormorant | C17: Bihua Chen | E17: 4012.7661
B18: Camber | E18: 3542.0446
B19: Casdin | E19: 2643.699
B20: Kynam Capital | E20: 1296.4212
B21: Palo Alto | E21: 1057
B22: Tang | C22: Kevin Tang | E22: 981.87468
B23: Adar1 | E23: 507.77477
B24: Oracle
B25: Flagship

Sheet Acquisitions
A1: Main
B2: Acquiree | C2: Acquirer | D2: Consideration | E2: Announce Date | F2: Close Date | G2: Notes
B3: SmithKline Beecham | C3: Glaxo Wellcome | D3: 76000 | E3: 2000 | G3: Merger of equals (182B)
B4: Celgene | C4: BMY | D4: 74000 | E4: 43468
B5: Wyeth | C5: PFE | D5: 68000 | E5: 39838
B6: Astra | C6: Zeneca | D6: 67000 | E6: 1999 | G6: Merger of equals.
B7: Aventis | C7: Sanofi | D7: 64000 | E7: 38103 | F7: 38103
B8: Allergan | C8: ABBV | D8: 63000 | E8: 43641
B9: Monsanto | C9: Bayer | D9: 63000 | E9: 2018
B10: Ciba-Geigy | C10: Sandoz | D10: 63000 | E10: 1996 | G10: Merger of equals to create Novartis.
B11: Shire | C11: Takeda | D11: 62000 | E11: 43473 | F11: 43473
B12: Pharmacia | C12: PFE | D12: 60000 | E12: 2002
B13: Genentech | C13: Roche | D13: 47000 | E13: 2019 | G13: Acquired publicly traded minority stake.
B14: Seagen | C14: SGEN | D14: 43000 | E14: 2023
B15: Schering-Plough | C15: MRK | D15: 41100 | E15: 2009
B16: Actavis Generics | C16: TEVA | D16: 40500 | E16: 2015
B17: Alcon | C17: Novartis | D17: 39000 | E17: 2008 | G17: Acquired 77% via Nestle
B18: Baxalta | C18: Shire | D18: 32000 | E18: 2016
B19: Actelion | C19: J&J | D19: 30000 | E19: 2017
B20: Horizon | C20: AMGN | D20: 27800 | E20: 2023
B21: Pharmacyclics | C21: ABBV | D21: 21000 | E21: 2015 | F21: 2015
B22: Immunomedics | C22: Gilead | D22: 21000
B23: Genzyme | C23: Sanofi | D23: 20100 | E23: 40590
B24: Hospira | C24: Pfizer | D24: 17000 | E24: 42036 | F24: 42250
B25: Immunex | C25: AMGN | D25: 16000 | E25: 37239 | F25: 37449
B26: MedImmune | C26: AZN | D26: 15600 | E26: 39196 | F26: 39196
B27: Salix | C27: Valeant | D27: 14500 | E27: 42058
B28: Medivation | C28: Pfizer | D28: 14000 | E28: 2016
B29: Karuna | C29: BMY | D29: 12700 | E29: 2023
B30: Kite | C30: Gilead | D30: 11900 | E30: 2017
B31: Vifor | C31: CSL | D31: 11700 | E31: 2021
B32: Biohaven | C32: Pfizer | D32: 11600 | E32: 2022
B33: Bioverativ | C33: Sanofi | D33: 11600 | E33: 43122
B34: Array | C34: Pfizer | D34: 11400 | E34: 43633
B35: Pharmasset | C35: Gilead | D35: 11000 | E35: 2011
B36: Immunogen | C36: ABBV | D36: 10100 | E36: 45260
B37: The Medicines Company | C37: NVS | D37: 9700 | E37: 2019
B38: Juno | C38: Celgene | D38: 9000 | E38: 2018
B39: AveXis | C39: NVS | D39: 8700 | E39: 2018
B40: Cerevel | C40: ABBV | D40: 8700 | F40: 45505
B41: Bausch & Lomb | C41: Valeant | D41: 8700 | E41: 41421
B42: Cubist | C42: MRK | D42: 8400 | E42: 2014
B43: Daiichi | C43: Sankyo | D43: 7700 | E43: 2005 | G43: Merger of equals.
B44: Fujisawa | C44: Yamanouchi | D44: 7600 | E44: 2004 | G44: Combination renamed Astellas.
B45: GW Pharmaceuticals | C45: Jazz | D45: 7200 | E45: 2021
B46: Cephalon | C46: TEVA | D46: 6800 | E46: 2011
B47: Arena | C47: Pfizer | D47: 6700 | E47: 44543
B48: ImClone | C48: Lilly | D48: 6500 | E48: 2008 | G48: Bristol also made an offer.
B49: IDEC | C49: Biogen | D49: 5800 | E49: 2003
B50: Global Blood | C50: Pfizer | D50: 5400 | F50: 44840
B51: Chiron | C51: Novartis | D51: 5100 | E51: 2005 | G51: Owned 40% or so
B52: Centocor | C52: J&J | D52: 4900 | E52: 1999
B53: Mirati | C53: MRTX | D53: 4800 | E53: 45207
B54: Ablynx | C54: Sanofi | D54: 4800 | E54: 43129
B55: Cymabay | C55: Gilead | D55: 4300 | E55: 2024
B56: Turning Point | C56: TPTX | D56: 4100 | E56: 44715
B57: OSI Pharmaceuticals | C57: Astellas | D57: 4000 | E57: 2010
B58: Idenix | C58: MRK | D58: 3850 | E58: 2014 | G58: Novartis spin-out? They owned 22% at acquisition.
B59: ChemoCentryx | C59: AMGN | D59: 3700 | E59: 44777
B60: Myogen | C60: Gilead | D60: 2500 | E60: 2006
B61: Medarex | C61: BMY | D61: 2400 | F61: 40057
B62: Scios | C62: J&J | D62: 2400 | E62: 2003
B63: ICOS | C63: Lilly | D63: 2300 | E63: 2006
B64: Genentech | C64: Roche | D64: 2100 | E64: 1990 | G64: Acquired 56% stake
B65: Icos | C65: Lilly | D65: 2100 | E65: 2006
B66: Imago (IMGO) | C66: MRK | D66: 1350 | E66: 44886
B67: Cougar | C67: J&J | D67: 1000 | E67: 39955
B68: Aiolos | C68: GSK | D68: 1000 | E68: 45300
B69: Aerie | C69: Alcon | D69: 770 | E69: 44796
B70: Sugen | C70: Pharmacia | D70: 650 | E70: 1999
B71: MiroBio | C71: Gilead | D71: 405 | E71: 44777
B72: DJS Antibodies | C72: ABBV
B73: Vividion | C73: Bayer | E73: 2021
B74: AskBio | C74: Bayer | E74: 2020
B75: BlueRock | C75: Bayer | E75: 2019
B76: WuXi Biologics | C76: 2269 HK | D76: 44.85 | E76: {=+D76*I76/HKD} -> 24515.288 | F76: =([198]Main!$J$5-[198]Main!$J$6)/HKD -> 991.71513 | G76: =+E76-F76 -> 23523.573 | H76: Q222 | I76: =+[198]Main!$J$3 -> 4263.5283 | J76: 45086
B77: Evotec | C77: EVO | D77: 12.2
B78: Reata | C78: RETA | D78: 92.93 | E78: 3490
B79: Provention | C79: PRVB | D79: 23.01 | E79: 2080
B80: Iveric | C80: ISEE | D80: 14.86 | E80: 2880
B81: EQRx | C81: EQRX | D81: 2.15 | E81: 1050
B82: Intercept | C82: ICPT
B83: Chinook | C83: KDNY
B84: Jnana | C84: Otsuka
B85: Elan
B86: ID Biomedical | C86: GSK
B87: Corixa | C87: GSK
B88: Crucell | C88: JNJ
B89: Bellus | C89: GSK
B90: Savient | C90: Horizon
C91: Horizon
B92: Ciba | C92: JR Geigy | E92: 1970
B93: Ivax
B94: HMR
B95: Alza
B96: Medicis
B97: Forward Pharma | C97: Biogen
B98: Hexal | C98: Novartis
B99: Serono | C99: Merck KgAA
B100: Zogenix | C100: UCB
...

Sheet Mergers
C2: 1849 | D2: 1850 | E2: 1851 | F2: 1852 | G2: 1853 | H2: 1854 | I2: 1855 | J2: 1856 | K2: 1857 | L2: 1858 | M2: 1859 | N2: 1860 | O2: 1861 | P2: 1862 | Q2: 1863 | R2: 1864 | S2: 1865 | T2: 1866 | U2: 1867 | V2: 1868 | W2: 1869 | X2: 1870 | Y2: 1871 | Z2: 1872 | AA2: 1873 | AB2: 1874 | AC2: 1875 | AD2: 1876 | AE2: 1877 | AF2: 1878 | AG2: 1879 | AH2: 1880 | AI2: 1881 | AJ2: 1882 | AK2: 1883 | AL2: 1884 | AM2: 1885 | AN2: 1886 | AO2: 1887 | AP2: 1888 | AQ2: =+AP2+1 -> 1889 | AR2: =+AQ2+1 -> 1890 | AS2: =+AR2+1 -> 1891 | AT2: =+AS2+1 -> 1892 | AU2: =+AT2+1 -> 1893 | AV2: =+AU2+1 -> 1894 | AW2: =+AV2+1 -> 1895 | AX2: =+AW2+1 -> 1896 | ... GA2: =+FZ2+1 -> 2029
B3: Johnson & Johnson | AP3: Founded
B4: Actelion
B5: Intercept
B6: Centocor
B7: Pharmacia | BM7: Founded in Sweden (actually Farmitalia Carlo Erba and Kabi, so goes back further) | DY7: Pharmacia | ED7: Pharmacia | EI7: Pharmacia | EJ7: Pharmacia | EK7: Pharmacia | EL7: Pharmacia | EM7: Pharmacia | EN7: Pharmacia | EO7: Pharmacia | EP7: Pharmacia | EQ7: Pharmacia | ER7: Pharmacia | ES7: Merged with Upjohn | ET7: Pharmacia-Upjohn | EU7: Pharmacia-Upjohn | EV7: Pharmacia-Upjohn | EW7: Pharmacia-Upjohn | EX7: Pharmacia | EY7: Pharmacia | EZ7: Pharmacia | FA7: Acquired by Pfizer | FB7: Pfizer | FC7: Pfizer | FD7: Pfizer | FE7: Pfizer | FF7: Pfizer | FG7: Acquires Wyeth/AHP | FH7: Pfizer | FI7: Pfizer | FJ7: Pfizer | FK7: Pfizer | FL7: Pfizer | FM7: Pfizer | FN7: Pfizer | FO7: Pfizer | FP7: Pfizer | FQ7: Pfizer | FR7: Pfizer | FS7: Pfizer | FT7: Pfizer | FU7: Pfizer | FV7: Pfizer | FW7: Pfizer
B8: Upjohn | AN8: Founded in Michigan | DY8: Upjohn | ED8: Upjohn | EI8: Upjohn | EJ8: Upjohn | EK8: Upjohn | EL8: Upjohn | EM8: Upjohn | EN8: Upjohn | EO8: Upjohn | EP8: Upjohn | EQ8: Upjohn | ER8: Upjohn | ES8: Merged with Pharmacia
B9: Monsanto | BC9: Founded | DY9: Monsanto | ED9: Monsanto | EI9: Acquires Searle | EJ9: Monsanto | EK9: Monsanto | EL9: Monsanto | EM9: Monsanto | EN9: Monsanto | EO9: Monsanto | EP9: Monsanto | EQ9: Monsanto | ER9: Monsanto | ES9: Monsanto | ET9: Monsanto | EU9: Monsanto | EV9: Monsanto | EW9: Merged with Pharmacia-Upjohn
B10: Searle | AP10: Founded | DY10: Searle | ED10: Searle | EI10: Acquired by Monsanto
B11: Sugen | EO11: Founded | EP11: Sugen | EQ11: Sugen | ER11: Sugen | ES11: Sugen | ET11: Sugen | EU11: Sugen | EV11: Sugen | EW11: Acquired by Pharmacia
B12: Pfizer | C12: Founded | DU12: Pfizer | DY12: Pfizer | ED12: Pfizer | EE12: Pfizer | EF12: Pfizer | EG12: Pfizer | EH12: Pfizer | EI12: Pfizer | EJ12: Pfizer | EK12: Pfizer | EL12: Pfizer | EM12: Pfizer | EN12: Pfizer | EO12: Pfizer | EP12: Pfizer | EQ12: Pfizer | ER12: Pfizer | ES12: Pfizer | ET12: Pfizer | EU12: Pfizer | EV12: Pfizer | EW12: Acquired Warner-Lambert | EX12: Pfizer | EY12: Pfizer | EZ12: Pfizer | FA12: Acquires Pharmacia
B13: William R. Warner and Company Limited | J13: Founded | CZ13: Renamed Warner-Hudnut, Inc | DE13: Warner merges with Lambert | DF13: Warner-Lambert | DT13: Warner-Lambert Acquires Parke-Davis | DU13: Warner-Lambert | DY13: Warner-Lambert | ED13: Warner-Lambert | EI13: Warner-Lambert | EJ13: Warner-Lambert | EK13: Warner-Lambert | EL13: Warner-Lambert | EM13: Warner-Lambert | EN13: Warner-Lambert | EO13: Warner-Lambert | EP13: Warner-Lambert | EQ13: Warner-Lambert | ER13: Warner-Lambert | ES13: Warner-Lambert | ET13: Warner-Lambert | EU13: Warner-Lambert | EV13: Warner-Lambert | EW13: Acquired by Pfizer
B14: Lambert Pharmacal Company | AI14: Founded | DE14: Lambert merges with Warner
B15: Parke-Davis | T15: Founded in Detroit | DT15: Parke-Davis acquired by Warner-Lambert
B16: American Home Products | N16: Founded | CF16: Acquires Wyeth | CG16: American Home Products | CS16: Acquires Ayerst | CT16: American Home Products | DY16: American Home Products | DZ16: American Home Products | EA16: American Home Products | EB16: American Home Products | EC16: American Home Products | ED16: American Home Products | EE16: American Home Products | EF16: American Home Products | EG16: American Home Products | EH16: American Home Products | EI16: American Home Products | EJ16: American Home Products | EK16: American Home Products | EL16: American Home Products | EM16: American Home Products | EN16: American Home Products | EO16: American Home Products | EP16: American Home Products | EQ16: American Home Products | ER16: Acquires American Cyanamid | ES16: American Home Products | ET16: American Home Products | EU16: American Home Products | EV16: American Home Products | EW16: American Home Products | EX16: American Home Products | EY16: American Home Products | EZ16: American Home Products | FA16: American Home Products | FB16: American Home Products | FC16: American Home Products | FD16: American Home Products | FE16: American Home Products | FF16: American Home Products | FG16: Acquired by Pfizer
B17: John Wyeth & Brother, Inc. | N17: Founded by brothers John & Frank Wyeth in Philadelphia. | CE17: Stuart Wyeth dies, bequeaths company to Harvard. | CF17: Sold to AHP for $2.9m.
B18: Ayerst, McKenna & Harrison Limited | CA18: Founded | CS18: Acquired by AHP
B19: Genetics Institute | ED19: Founded | EP19: Acquired by AHP
B20: American Cyanamid | BI20: Founded by Frank Washburn and Charles Baker | CE20: Acquired Lederle | CF20: American Cyanamid | CG20: American Cyanamid | CH20: American Cyanamid | CI20: American Cyanamid | CJ20: American Cyanamid | CK20: American Cyanamid | CL20: American Cyanamid | CM20: American Cyanamid | CN20: American Cyanamid | CO20: American Cyanamid | CP20: American Cyanamid | CQ20: American Cyanamid | CR20: American Cyanamid | CS20: American Cyanamid | CT20: American Cyanamid | CU20: American Cyanamid | CV20: American Cyanamid | CW20: American Cyanamid | CX20: American Cyanamid | CY20: American Cyanamid | CZ20: American Cyanamid | DA20: American Cyanamid | DB20: American Cyanamid | DC20: American Cyanamid | DD20: American Cyanamid | DE20: American Cyanamid | DF20: American Cyanamid | DG20: American Cyanamid | DH20: American Cyanamid | DI20: American Cyanamid | DJ20: American Cyanamid | DK20: American Cyanamid | DL20: American Cyanamid | DM20: American Cyanamid | DN20: American Cyanamid | DO20: American Cyanamid | DP20: American Cyanamid | DQ20: American Cyanamid | DR20: American Cyanamid | DS20: American Cyanamid | DT20: American Cyanamid | DU20: American Cyanamid | DV20: American Cyanamid | DW20: American Cyanamid | DX20: American Cyanamid | DY20: American Cyanamid | DZ20: American Cyanamid | EA20: American Cyanamid | EB20: American Cyanamid | EC20: American Cyanamid | ED20: American Cyanamid | EE20: American Cyanamid | EF20: American Cyanamid | EG20: American Cyanamid | EH20: American Cyanamid | EI20: American Cyanamid | EJ20: American Cyanamid | EK20: American Cyanamid | EL20: American Cyanamid | EM20: American Cyanamid | EN20: American Cyanamid | EO20: American Cyanamid | EP20: American Cyanamid | EQ20: American Cyanamid | ER20: Acquired by AHP
B21: Lederle Antitoxin Laboratories | BH21: Founded | CE21: Acquired by American Cyanamid
B22: Hospira (2004-2015) | FB22: Spun-out of Abbott | FC22: Hospira | FD22: Hospira | FE22: Hospira | FF22: Hospira | FG22: Hospira
B23: Medivation (2004-2016) | FB23: Founded | FC23: Medivation | FD23: Medivation | FE23: Medivation | FF23: Medivation | FG23: Medivation | FH23: Medivation | FI23: Medivation | FJ23: Medivation | FK23: Medivation | FL23: Medivation | FM23: Medivation | FN23: Acquired by Pfizer
B24: Arena (1997 - 2022) | EU24: Founded | EV24: Arena | EW24: Arena | EX24: Arena | EY24: Arena | EZ24: Arena | FA24: Arena | FB24: Arena | FC24: Arena | FD24: Arena | FE24: Arena | FF24: Arena | FG24: Arena | FH24: Arena | FI24: Arena | FJ24: Arena | FK24: Arena | FL24: Arena | FM24: Arena | FN24: Arena | FO24: Arena | FP24: Arena | FQ24: Arena | FR24: Arena | FS24: Arena | FT24: Acquired by Pfizer
B25: Biohaven (2013-2022) | FK25: Founded | FL25: Biohaven | FM25: Biohaven | FN25: Biohaven | FO25: Biohaven | FP25: Biohaven | FQ25: Biohaven | FR25: Biohaven | FS25: Biohaven | FT25: Acquired by Pfizer
B26: Seattle Genetics (1997-2023) | EU26: Founded | EV26: Seattle Genetics | EW26: Seattle Genetics | EX26: Seattle Genetics | EY26: Seattle Genetics | EZ26: Seattle Genetics | FA26: Seattle Genetics | FB26: Seattle Genetics | FC26: Seattle Genetics | FD26: Seattle Genetics | FE26: Seattle Genetics | FF26: Seattle Genetics | FG26: Seattle Genetics | FH26: Seattle Genetics | FI26: Seattle Genetics | FJ26: Seattle Genetics | FK26: Seattle Genetics | FL26: Seattle Genetics | FM26: Seattle Genetics | FN26: Seattle Genetics | FO26: Seattle Genetics | FP26: Seattle Genetics | FQ26: Seattle Genetics | FR26: Seattle Genetics | FS26: Seattle Genetics | FT26: Seattle Genetics | FU26: Acquired by Pfizer
B27: MedImmune
B28: Aviron
B29: Astra
B30: Zeneca
B31: Merck KGaA
B32: Merck & Co
B33: Schering-Plough
B34: The Medicines Company
B35: Chiron
B36: CIBA | D36: Founded 1850s | DT36: MERGED WITH JR. Geigy SA | DU36: Ciba-Geigy
B37: J.R. Geigy | C37: Founded 1758 | DT37: MERGED with CIBA
B38: AbbVie
B39: Abbott Laboratories | AP39: Founded | FB39: Abbott Labs
B40: Gilead | EK40: Founded
B41: Amgen | ED41: Founded
B42: Genentech | DZ42: Founded
B43: Roche | AX43: Founded
B44: Squibb | L44: Founded | EM44: Merged with Bristol-Myers | EN44: Bristol-Myers Squibb | EQ44: Bristol-Myers Squibb | EU44: Bristol-Myers Squibb
B45: Bristol-Myers | AO45: Founded as Clinton Pharmaceutical Company | AZ45: Renamed Bristol, Myers Company | BA45: Renamed Bristol-Myers | CE45: IPO | EM45: Merged with Squibb
B46: Sanofi | DW46: Founded as subsidiary of Elf Aquitaine | EX46: Sanofi-Synthelabo | EZ46: Sanofi-Synthelabo | FB46: Sanofi-Synthelabo
B47: Laboratoires Dausse | C47: Founded 1834 | DT47: Merged with Laboratoires Robert & Carrière to create Synthelabo | DU47: Synthelabo | EW47: Merged with Sanofi to create Sanofi-Synthelabo
B48: Laboratoires Robert & Carrière | BA48: Founded | DT48: Merged with Laboratoires Dausse to create Synthelabo
B49: Glaxo
B50: Wellcome
B51: SmithKline
B52: Beecham
B53: Rhone-Poulenc
B54: Hoechst | Q54: Founded
B55: Wittmann et Poulenc Jeune | N55: Founded
B56: Eli Lilly | AD56: Founded
B57: ImClone
B58: ICOS
B59: Novo Nordisk | BY59: Founded
B60: Takeda
B61: Daiichi
B62: Yamanouchi
B63: Fujisawa
B64: Bayer
B65: Regeneron
B66: Biogen

Sheet Bankruptcies
A1: Main
B2: Savient
B3: Aravive
B4: Tricida
